{"code":200,"msg":"success","data":[{"id":18661,"createTime":"2019-10-31 15:36:40","topicId":null,"tagId":1762,"rule":1,"weight":1,"sort":370,"accuracy":0.0,"content":"<p><span style=\";font-family:宋体;font-size:14px\"><span style=\"font-family:宋体\">男性农民，</span>30岁，5月中旬发病，起病急，发冷，发热，全身肌痛，5天后在某地医院诊断为败血症休克，经静脉补液及氨苄青霉素静点，次日血压正常。但病情加重，呃逆，呕吐，尿少入院，体检：体温37.3℃，血压150/100mmHg，皮肤黏膜有瘀点，球结膜充血，水肿，心肺未见异常，肝大肋下1.0cm，腰部有叩击痛，化验：白细胞50×109／L，中性85％，淋巴15％，血小板3×109／L，尿蛋白（+++），最可能的诊断</span></p><p><br/></p>","trueCnt":0,"falseCnt":0,"analysis":"<p><span style=\";font-family:宋体;font-size:14px\"><span style=\"font-family:宋体\">患者</span>5月中旬发病，出现发热、皮肤黏膜瘀点、球结膜充血，腰部叩击痛，白细胞大量增多，大量蛋白尿，首先考虑肾综合征出血热。</span></p><p><span style=\";font-family:宋体;font-size:14px\"><span style=\"font-family:宋体\">肾综合征出血热临床表现：</span></span></p><p><span style=\";font-family:宋体;font-size:14px\">1、三大主症：发热、出血、肾脏损害</span></p><p><span style=\";font-family:宋体;font-size:14px\">2、五期经过：①发热期：三痛“头痛、腰痛、眼眶痛”；三红“面部、颈部、上胸部皮肤潮红”；</span></p><p><span style=\";font-family:宋体;font-size:14px\">②低血压休克期、③少尿期、④多尿期、⑤恢复期</span></p><p><span style=\";font-family:宋体;font-size:14px\"><span style=\"font-family:宋体\">实验室检查：</span></span></p><p><span style=\";font-family:宋体;font-size:14px\">①血常规：白细胞、中性粒细胞升高</span></p><p><span style=\";font-family:宋体;font-size:14px\">②尿常规：大量尿蛋白</span></p><p><span style=\";font-family:宋体;font-size:14px\">③凝血功能障碍</span></p><p><br/></p>","topic":null,"options":[{"id":87451,"delFlag":false,"createTime":"2019-10-31 15:36:40","updateTime":"2019-10-31 15:36:40","isTrue":false,"questionId":18661,"content":"<p><span style=\";font-family:宋体;font-size:14px\"><span style=\"font-family:宋体\">钩端螺旋体病</span></span></p>","selectCnt":0},{"id":87452,"delFlag":false,"createTime":"2019-10-31 15:36:40","updateTime":"2019-10-31 15:36:40","isTrue":false,"questionId":18661,"content":"<p><span style=\";font-family:宋体;font-size:14px\"><span style=\"font-family:宋体\">败血症并感染性休克</span></span></p>","selectCnt":0},{"id":87453,"delFlag":false,"createTime":"2019-10-31 15:36:40","updateTime":"2019-10-31 15:36:40","isTrue":false,"questionId":18661,"content":"<p><span style=\";font-family:宋体;font-size:14px\"><span style=\"font-family:宋体\">伤寒并溶血性尿毒综合征</span></span></p>","selectCnt":0},{"id":87454,"delFlag":false,"createTime":"2019-10-31 15:36:40","updateTime":"2019-10-31 15:36:40","isTrue":false,"questionId":18661,"content":"<p><span style=\";font-family:宋体;font-size:14px\"><span style=\"font-family:宋体\">急性粒细胞性白血病</span></span></p>","selectCnt":0},{"id":87455,"delFlag":false,"createTime":"2019-10-31 15:36:40","updateTime":"2019-10-31 15:36:40","isTrue":true,"questionId":18661,"content":"<p><span style=\";font-family:宋体;font-size:14px\"><span style=\"font-family:宋体\">肾综合征出血热</span></span></p>","selectCnt":0}],"tags":[{"id":1762,"delFlag":false,"createTime":"2019-10-30 09:54:17","updateTime":"2019-10-30 09:54:17","name":"192","questionCnt":150,"tagTypeId":46},{"id":946,"delFlag":false,"createTime":"2019-06-09 11:31:57","updateTime":"2019-06-09 11:31:57","name":"泌尿A2","questionCnt":24,"tagTypeId":47}],"hasCollect":false,"userAnswer":null,"questionPath":null},{"id":18659,"createTime":"2019-10-31 15:31:58","topicId":null,"tagId":1762,"rule":1,"weight":1,"sort":369,"accuracy":0.0,"content":"<p><span style=\";font-family:宋体;font-size:14px\"><span style=\"font-family:宋体\">女，</span>47岁，慢性肾炎病史多年，近2年经常出现双下肢浮肿，一直服潘生丁及氢氯噻嗪治疗。近一周感觉腹胀，双下肢无力，首先考虑的是</span></p><p><br/></p>","trueCnt":0,"falseCnt":0,"analysis":"<p><span style=\"font-family: 宋体;letter-spacing: 0;font-size: 14px\"><span style=\"font-family:宋体\">氢氯噻嗪作用于肾远曲小管近端和髓袢升支远端，抑制钠和钾的重吸收，长期服用易引起低钾血症。低钾血症可致骨骼肌及胃肠道平滑肌细胞超极化阻滞、兴奋性降低，引起骨骼肌无力和发作性软瘫、肠蠕动减慢，可表现为食欲缺乏、腹胀、恶心和便秘。因此本例患者应首先考虑诊断为低钾血症</span></span><span style=\"font-family: 宋体;letter-spacing: 0;font-size: 14px\"><span style=\"font-family:宋体\">。</span></span></p><p><br/></p>","topic":null,"options":[{"id":87441,"delFlag":false,"createTime":"2019-10-31 15:31:58","updateTime":"2019-10-31 15:31:58","isTrue":false,"questionId":18659,"content":"<p><span style=\";font-family:宋体;font-size:14px\"><span style=\"font-family:宋体\">肾功能严重减退</span></span></p>","selectCnt":0},{"id":87442,"delFlag":false,"createTime":"2019-10-31 15:31:58","updateTime":"2019-10-31 15:31:58","isTrue":true,"questionId":18659,"content":"<p><span style=\";font-family:宋体;font-size:14px\"><span style=\"font-family:宋体\">低钾血症</span></span></p>","selectCnt":0},{"id":87443,"delFlag":false,"createTime":"2019-10-31 15:31:58","updateTime":"2019-10-31 15:31:58","isTrue":false,"questionId":18659,"content":"<p><span style=\";font-family:宋体;font-size:14px\"><span style=\"font-family:宋体\">高血压</span></span></p>","selectCnt":0},{"id":87444,"delFlag":false,"createTime":"2019-10-31 15:31:58","updateTime":"2019-10-31 15:31:58","isTrue":false,"questionId":18659,"content":"<p><span style=\";font-family:宋体;font-size:14px\"><span style=\"font-family:宋体\">酸中毒</span></span></p>","selectCnt":0},{"id":87445,"delFlag":false,"createTime":"2019-10-31 15:31:58","updateTime":"2019-10-31 15:31:58","isTrue":false,"questionId":18659,"content":"<p><span style=\";font-family:宋体;font-size:14px\"><span style=\"font-family:宋体\">药物中毒</span></span></p>","selectCnt":0}],"tags":[{"id":1762,"delFlag":false,"createTime":"2019-10-30 09:54:17","updateTime":"2019-10-30 09:54:17","name":"192","questionCnt":150,"tagTypeId":46},{"id":946,"delFlag":false,"createTime":"2019-06-09 11:31:57","updateTime":"2019-06-09 11:31:57","name":"泌尿A2","questionCnt":24,"tagTypeId":47}],"hasCollect":false,"userAnswer":null,"questionPath":null},{"id":18658,"createTime":"2019-10-31 15:30:58","topicId":null,"tagId":1762,"rule":1,"weight":1,"sort":368,"accuracy":0.0,"content":"<p><span style=\";font-family:宋体;font-size:14px\"><span style=\"font-family:宋体\">女，</span>40 岁。畏寒、高热伴腰痛。尿频、尿急</span><span style=\";font-family:宋体;font-size:14px\"><span style=\"font-family:宋体\">、</span></span><span style=\";font-family:宋体;font-size:14px\"><span style=\"font-family:宋体\">尿痛</span> 2 天。查体：左侧肾区有压痛和叩击痛，尿 WBC40-50/HP，白细胞管型 5/LP。血WBC15.4×109L，N0.87。最可能的诊断是</span></p><p><br/></p>","trueCnt":0,"falseCnt":0,"analysis":"<p><span style=\";font-family:宋体;font-size:14px\"><span style=\"font-family:宋体\">患者</span></span><span style=\";font-family:宋体;font-size:14px\"><span style=\"font-family:宋体\">尿频、尿急</span></span><span style=\";font-family:宋体;font-size:14px\"><span style=\"font-family:宋体\">、</span></span><span style=\";font-family:宋体;font-size:14px\"><span style=\"font-family:宋体\">尿痛</span></span><span style=\";font-family:宋体;font-size:14px\"><span style=\"font-family:宋体\">；</span></span><span style=\";font-family:宋体;font-size:14px\"><span style=\"font-family:宋体\">高热伴腰痛</span></span><span style=\";font-family:宋体;font-size:14px\"><span style=\"font-family:宋体\">；</span></span><span style=\";font-family:宋体;font-size:14px\"><span style=\"font-family:宋体\">肾区有压痛和叩击痛</span></span><span style=\";font-family:宋体;font-size:14px\"><span style=\"font-family:宋体\">，</span></span><span style=\";font-family:宋体;font-size:14px\"><span style=\"font-family:宋体\">都是急性肾盂肾炎的典型症状，故选</span>C。</span></p><p><br/></p>","topic":null,"options":[{"id":87436,"delFlag":false,"createTime":"2019-10-31 15:30:58","updateTime":"2019-10-31 15:30:58","isTrue":false,"questionId":18658,"content":"<p><span style=\";font-family:宋体;font-size:14px\"><span style=\"font-family:宋体\">急性膀胱炎</span></span></p>","selectCnt":0},{"id":87437,"delFlag":false,"createTime":"2019-10-31 15:30:58","updateTime":"2019-10-31 15:30:58","isTrue":false,"questionId":18658,"content":"<p><span style=\";font-family:宋体;font-size:14px\"><span style=\"font-family:宋体\">尿路结石</span></span></p>","selectCnt":0},{"id":87438,"delFlag":false,"createTime":"2019-10-31 15:30:58","updateTime":"2019-10-31 15:30:58","isTrue":true,"questionId":18658,"content":"<p><span style=\";font-family:宋体;font-size:14px\"><span style=\"font-family:宋体\">急性肾盂肾炎</span></span></p>","selectCnt":0},{"id":87439,"delFlag":false,"createTime":"2019-10-31 15:30:58","updateTime":"2019-10-31 15:30:58","isTrue":false,"questionId":18658,"content":"<p><span style=\";font-family:宋体;font-size:14px\"><span style=\"font-family:宋体\">急性肾小球肾炎</span></span></p>","selectCnt":0},{"id":87440,"delFlag":false,"createTime":"2019-10-31 15:30:58","updateTime":"2019-10-31 15:30:58","isTrue":false,"questionId":18658,"content":"<p><span style=\";font-family:宋体;font-size:14px\"><span style=\"font-family:宋体\">尿路综合症</span></span></p>","selectCnt":0}],"tags":[{"id":1762,"delFlag":false,"createTime":"2019-10-30 09:54:17","updateTime":"2019-10-30 09:54:17","name":"192","questionCnt":150,"tagTypeId":46},{"id":946,"delFlag":false,"createTime":"2019-06-09 11:31:57","updateTime":"2019-06-09 11:31:57","name":"泌尿A2","questionCnt":24,"tagTypeId":47}],"hasCollect":false,"userAnswer":null,"questionPath":null},{"id":18651,"createTime":"2019-10-31 15:25:17","topicId":null,"tagId":1762,"rule":1,"weight":1,"sort":361,"accuracy":0.0,"content":"<p><span style=\";font-family:宋体;font-size:14px\"><span style=\"font-family:宋体\">男，</span>59 岁。排尿困难 2 年。2 年来排尿困难逐渐加重，表现为尿线变细，尿滴沥。夜尿3-4次。无尿痛及肉眼血尿，直肠指检及B 超诊断为前列腺增生，确定排尿梗阻程度的有效检查方法是</span></p><p><br/></p>","trueCnt":0,"falseCnt":0,"analysis":"<p><span style=\";font-family:宋体;font-size:14px\"><span style=\"font-family:宋体\">根据病史，患者为前列腺增生，可以确定前列腺增生病人排尿的梗阻程度。检查时要求排尿量在</span>150ml以上,如最大尿流率&lt;15m/s表明排尿不畅;如&lt;10ml/s则表明梗阻较为严重，常是手术指征之一。如需进一步了解逼尿肌功能,明确排尿困难是否由于其他膀胱神经源性病变所致,应行尿流动力学检查。</span></p><p><br/></p>","topic":null,"options":[{"id":87401,"delFlag":false,"createTime":"2019-10-31 15:25:17","updateTime":"2019-10-31 15:25:17","isTrue":true,"questionId":18651,"content":"<p><span style=\";font-family:宋体;font-size:14px\"><span style=\"font-family:宋体\">尿流率检查</span></span></p>","selectCnt":0},{"id":87402,"delFlag":false,"createTime":"2019-10-31 15:25:17","updateTime":"2019-10-31 15:25:17","isTrue":false,"questionId":18651,"content":"<p><span style=\";font-family:宋体;font-size:14px\"><span style=\"font-family:宋体\">膀胱镜</span></span></p>","selectCnt":0},{"id":87403,"delFlag":false,"createTime":"2019-10-31 15:25:17","updateTime":"2019-10-31 15:25:17","isTrue":false,"questionId":18651,"content":"<p><span style=\";font-family:宋体;font-size:14px\"><span style=\"font-family:宋体\">残余尿测定</span></span></p>","selectCnt":0},{"id":87404,"delFlag":false,"createTime":"2019-10-31 15:25:17","updateTime":"2019-10-31 15:25:17","isTrue":false,"questionId":18651,"content":"<p><span style=\";font-family:宋体;font-size:14px\">CT&nbsp;</span></p>","selectCnt":0},{"id":87405,"delFlag":false,"createTime":"2019-10-31 15:25:17","updateTime":"2019-10-31 15:25:17","isTrue":false,"questionId":18651,"content":"<p><span style=\";font-family:宋体;font-size:14px\">MRI</span></p>","selectCnt":0}],"tags":[{"id":1762,"delFlag":false,"createTime":"2019-10-30 09:54:17","updateTime":"2019-10-30 09:54:17","name":"192","questionCnt":150,"tagTypeId":46},{"id":946,"delFlag":false,"createTime":"2019-06-09 11:31:57","updateTime":"2019-06-09 11:31:57","name":"泌尿A2","questionCnt":24,"tagTypeId":47}],"hasCollect":false,"userAnswer":null,"questionPath":null},{"id":18649,"createTime":"2019-10-31 15:23:03","topicId":null,"tagId":1762,"rule":1,"weight":1,"sort":359,"accuracy":0.0,"content":"<p><span style=\";font-family:宋体;font-size:14px\"><span style=\"font-family:宋体\">男，</span>78岁。水肿、大量蛋白尿3周余，肾活检示膜性肾病，近2日出现有下肢水肿加重，腰痛。应首先考虑的并发症是</span></p><p><br/></p>","trueCnt":0,"falseCnt":0,"analysis":"<p><span style=\";font-family:宋体;font-size:14px\"><span style=\"font-family:宋体\">膜性肾病最容易发生肾静脉血栓的并发症，本体患者诊断膜性肾病，又出现</span></span><span style=\";font-family:宋体;font-size:14px\"><span style=\"font-family:宋体\">水肿加重，腰痛</span></span><span style=\";font-family:宋体;font-size:14px\"><span style=\"font-family:宋体\">，</span></span><span style=\";font-family:宋体;font-size:14px\"><span style=\"font-family:宋体\">出现了静脉血栓的并发症，故选</span>C。</span></p><p><br/></p>","topic":null,"options":[{"id":87391,"delFlag":false,"createTime":"2019-10-31 15:23:03","updateTime":"2019-10-31 15:23:03","isTrue":false,"questionId":18649,"content":"<p><span style=\";font-family:宋体;font-size:14px\"><span style=\"font-family:宋体\">动脉栓塞</span></span></p>","selectCnt":0},{"id":87392,"delFlag":false,"createTime":"2019-10-31 15:23:03","updateTime":"2019-10-31 15:23:03","isTrue":false,"questionId":18649,"content":"<p><span style=\";font-family:宋体;font-size:14px\"><span style=\"font-family:宋体\">痛风发作</span></span></p>","selectCnt":0},{"id":87393,"delFlag":false,"createTime":"2019-10-31 15:23:03","updateTime":"2019-10-31 15:23:03","isTrue":true,"questionId":18649,"content":"<p><span style=\";font-family:宋体;font-size:14px\"><span style=\"font-family:宋体\">静脉血栓</span></span></p>","selectCnt":0},{"id":87394,"delFlag":false,"createTime":"2019-10-31 15:23:03","updateTime":"2019-10-31 15:23:03","isTrue":false,"questionId":18649,"content":"<p><span style=\";font-family:宋体;font-size:14px\"><span style=\"font-family:宋体\">静脉曲张</span></span></p>","selectCnt":0},{"id":87395,"delFlag":false,"createTime":"2019-10-31 15:23:03","updateTime":"2019-10-31 15:23:03","isTrue":false,"questionId":18649,"content":"<p><font face=\"宋体\"><span style=\"font-size: 14px;\">淋巴管炎</span></font></p><p></p>","selectCnt":0}],"tags":[{"id":1762,"delFlag":false,"createTime":"2019-10-30 09:54:17","updateTime":"2019-10-30 09:54:17","name":"192","questionCnt":150,"tagTypeId":46},{"id":946,"delFlag":false,"createTime":"2019-06-09 11:31:57","updateTime":"2019-06-09 11:31:57","name":"泌尿A2","questionCnt":24,"tagTypeId":47}],"hasCollect":false,"userAnswer":null,"questionPath":null},{"id":18648,"createTime":"2019-10-31 15:22:02","topicId":null,"tagId":1762,"rule":1,"weight":1,"sort":358,"accuracy":0.0,"content":"<p><span style=\";font-family:宋体;font-size:14px\"><span style=\"font-family:宋体\">男，</span>70岁，进行性排尿困难3年，加重伴尿失禁2天，此尿失禁为</span></p><p><br/></p>","trueCnt":0,"falseCnt":0,"analysis":"<p><span style=\";font-family:宋体;font-size:14px\"><span style=\"font-family:宋体\">老年患者进行性排尿困难，应考虑前列腺增生。前列腺增生患者早期主要表现为尿频，尿道梗阻可诱发逼尿肌功能受损，膀胱顺应性降低，尿频明显可并发急迫性尿失禁（</span>E）。晚期，主要表现为排尿困难，当梗阻加重，膀胱过度充盈时，可出现充盈性尿失禁（A）。可见前列腺增生早期表现为尿频+急迫性尿失禁，晚期表现为排尿困难+充盈性尿失禁，根据题意，正确答案为A而不是E</span><span style=\";font-family:宋体;font-size:14px\"><span style=\"font-family:宋体\">。</span></span></p><p><br/></p>","topic":null,"options":[{"id":87386,"delFlag":false,"createTime":"2019-10-31 15:22:02","updateTime":"2019-10-31 15:22:02","isTrue":true,"questionId":18648,"content":"<p><span style=\";font-family:宋体;font-size:14px\"><span style=\"font-family:宋体\">充盈性尿失禁</span></span></p>","selectCnt":0},{"id":87387,"delFlag":false,"createTime":"2019-10-31 15:22:02","updateTime":"2019-10-31 15:22:02","isTrue":false,"questionId":18648,"content":"<p></p><p><span style=\";font-family:宋体;font-size:14px\"><span style=\"font-family:宋体\">压力性尿失禁</span></span></p>","selectCnt":0},{"id":87388,"delFlag":false,"createTime":"2019-10-31 15:22:02","updateTime":"2019-10-31 15:22:02","isTrue":false,"questionId":18648,"content":"<p><span style=\";font-family:宋体;font-size:14px\"><span style=\"font-family:宋体\">真性尿失禁你</span></span></p>","selectCnt":0},{"id":87389,"delFlag":false,"createTime":"2019-10-31 15:22:02","updateTime":"2019-10-31 15:22:02","isTrue":false,"questionId":18648,"content":"<p><span style=\";font-family:宋体;font-size:14px\"><span style=\"font-family:宋体\">混合型尿失禁</span></span></p>","selectCnt":0},{"id":87390,"delFlag":false,"createTime":"2019-10-31 15:22:02","updateTime":"2019-10-31 15:22:02","isTrue":false,"questionId":18648,"content":"<p><span style=\";font-family:宋体;font-size:14px\"><span style=\"font-family:宋体\">急迫性尿失禁</span></span></p>","selectCnt":0}],"tags":[{"id":1762,"delFlag":false,"createTime":"2019-10-30 09:54:17","updateTime":"2019-10-30 09:54:17","name":"192","questionCnt":150,"tagTypeId":46},{"id":946,"delFlag":false,"createTime":"2019-06-09 11:31:57","updateTime":"2019-06-09 11:31:57","name":"泌尿A2","questionCnt":24,"tagTypeId":47}],"hasCollect":false,"userAnswer":null,"questionPath":null},{"id":18511,"createTime":"2019-10-31 10:51:40","topicId":null,"tagId":1761,"rule":1,"weight":1,"sort":346,"accuracy":0.0,"content":"<p style=\";padding: 0;vertical-align: baseline\"><span style=\"font-family: 宋体;letter-spacing: 0;font-size: 16px\"><span style=\"font-family:宋体\">女，</span>17岁。鼻塞、流涕、咽痛、发热1天后出现肉眼血尿，伴随面部水肿。BP140/100mmHg，尿蛋白（+++），为明确诊断，最有价值的进一步检查是</span></p><p><br/></p>","trueCnt":0,"falseCnt":0,"analysis":"<p style=\";padding: 0;vertical-align: baseline\"><span style=\"font-family: 宋体;color: rgb(51, 51, 51);letter-spacing: 0;font-size: 16px\"><span style=\"font-family:宋体\">根据前驱感染病史，及血尿、蛋白尿、水肿、</span></span><a href=\"http://www.med66.com/jibing/gaoxueya/\" title=\"高血压\"><span style=\"font-family: 宋体;letter-spacing: 0;font-size: 16px\"><span style=\"font-family:宋体\">高血压</span></span></a><span style=\"font-family: 宋体;color: rgb(51, 51, 51);letter-spacing: 0;font-size: 16px\"><span style=\"font-family:宋体\">，诊断为急性肾小球肾炎，确诊依靠肾活检。</span></span></p><p><br/></p>","topic":null,"options":[{"id":86701,"delFlag":false,"createTime":"2019-10-31 10:51:40","updateTime":"2019-10-31 10:51:40","isTrue":false,"questionId":18511,"content":"<p style=\"padding: 0px; vertical-align: baseline;\"><span style=\"font-family: 宋体;letter-spacing: 0;font-size: 16px\"><span style=\"font-family:宋体\">双肾</span>CT</span></p>","selectCnt":0},{"id":86702,"delFlag":false,"createTime":"2019-10-31 10:51:40","updateTime":"2019-10-31 10:51:40","isTrue":false,"questionId":18511,"content":"<p style=\"padding: 0px; vertical-align: baseline;\"><span style=\"font-family: 宋体;letter-spacing: 0;font-size: 16px\"><span style=\"font-family:宋体\">肾脏</span>B超</span></p>","selectCnt":0},{"id":86703,"delFlag":false,"createTime":"2019-10-31 10:51:40","updateTime":"2019-10-31 10:51:40","isTrue":false,"questionId":18511,"content":"<p style=\"padding: 0px; vertical-align: baseline;\"><span style=\"font-family: 宋体;letter-spacing: 0;font-size: 16px\">24小时尿蛋白定量</span></p>","selectCnt":0},{"id":86704,"delFlag":false,"createTime":"2019-10-31 10:51:40","updateTime":"2019-10-31 10:51:40","isTrue":true,"questionId":18511,"content":"<p style=\"padding: 0px; vertical-align: baseline;\"><span style=\"font-family: 宋体;letter-spacing: 0;font-size: 16px\"><span style=\"font-family:宋体\">肾活检</span></span></p>","selectCnt":0},{"id":86705,"delFlag":false,"createTime":"2019-10-31 10:51:40","updateTime":"2019-10-31 10:51:40","isTrue":false,"questionId":18511,"content":"<p style=\"padding: 0px; vertical-align: baseline;\"><span style=\"font-family: 宋体;letter-spacing: 0;font-size: 16px\"><span style=\"font-family:宋体\">尿沉渣镜检</span></span></p>","selectCnt":0}],"tags":[{"id":1761,"delFlag":false,"createTime":"2019-10-30 09:54:12","updateTime":"2019-10-30 09:54:12","name":"191","questionCnt":150,"tagTypeId":46},{"id":946,"delFlag":false,"createTime":"2019-06-09 11:31:57","updateTime":"2019-06-09 11:31:57","name":"泌尿A2","questionCnt":24,"tagTypeId":47}],"hasCollect":false,"userAnswer":null,"questionPath":null},{"id":18510,"createTime":"2019-10-31 10:50:56","topicId":null,"tagId":1761,"rule":1,"weight":1,"sort":345,"accuracy":0.0,"content":"<p style=\";padding: 0;vertical-align: baseline\"><span style=\"font-family: 宋体;letter-spacing: 0;font-size: 16px\"><span style=\"font-family:宋体\">女，</span>42岁，肉眼血尿1月余。IVU显示双肾功能正常，右肾盂有充盈缺损1.5*1.2cm，尿细胞学检查发现肿瘤细胞。治疗方法首选</span></p><p><br/></p>","trueCnt":0,"falseCnt":0,"analysis":"<p style=\";padding: 0;vertical-align: baseline\"><span style=\";font-family:宋体;font-size:16px\"><span style=\"font-family:宋体\">解析</span></span><span style=\";font-family:宋体;font-size:16px\"><span style=\"font-family:宋体\">：</span></span><span style=\";font-family:宋体;font-size:16px\"><span style=\"font-family:宋体\">肾盂充盈缺损，提示诊断为肾盂癌。治疗首选手术治疗，标准的手术方法是切除患肾及全长输尿管</span></span><span style=\";font-family:宋体;font-size:16px\"><span style=\"font-family:宋体\">。</span></span></p><p><br/></p>","topic":null,"options":[{"id":86696,"delFlag":false,"createTime":"2019-10-31 10:50:56","updateTime":"2019-10-31 10:50:56","isTrue":false,"questionId":18510,"content":"<p style=\"padding: 0px; vertical-align: baseline;\"><span style=\"font-family: 宋体;letter-spacing: 0;font-size: 16px\"><span style=\"font-family:宋体\">放疗</span></span></p>","selectCnt":0},{"id":86697,"delFlag":false,"createTime":"2019-10-31 10:50:56","updateTime":"2019-10-31 10:50:56","isTrue":true,"questionId":18510,"content":"<p style=\"padding: 0px; vertical-align: baseline;\"><span style=\"font-family: 宋体;letter-spacing: 0;font-size: 16px\"><span style=\"font-family:宋体\">右肾</span>+输尿管全切术</span></p>","selectCnt":0},{"id":86698,"delFlag":false,"createTime":"2019-10-31 10:50:56","updateTime":"2019-10-31 10:50:56","isTrue":false,"questionId":18510,"content":"<p style=\"padding: 0px; vertical-align: baseline;\"><span style=\"font-family: 宋体;letter-spacing: 0;font-size: 16px\"><span style=\"font-family:宋体\">化疗</span></span></p>","selectCnt":0},{"id":86699,"delFlag":false,"createTime":"2019-10-31 10:50:56","updateTime":"2019-10-31 10:50:56","isTrue":false,"questionId":18510,"content":"<p style=\"padding: 0px; vertical-align: baseline;\"><span style=\"font-family: 宋体;letter-spacing: 0;font-size: 16px\"><span style=\"font-family:宋体\">右肾切除术</span></span></p>","selectCnt":0},{"id":86700,"delFlag":false,"createTime":"2019-10-31 10:50:56","updateTime":"2019-10-31 10:50:56","isTrue":false,"questionId":18510,"content":"<p style=\"padding: 0px; vertical-align: baseline;\"><span style=\"font-family: 宋体;letter-spacing: 0;font-size: 16px\"><span style=\"font-family:宋体\">肿瘤切除术</span></span></p>","selectCnt":0}],"tags":[{"id":1761,"delFlag":false,"createTime":"2019-10-30 09:54:12","updateTime":"2019-10-30 09:54:12","name":"191","questionCnt":150,"tagTypeId":46},{"id":946,"delFlag":false,"createTime":"2019-06-09 11:31:57","updateTime":"2019-06-09 11:31:57","name":"泌尿A2","questionCnt":24,"tagTypeId":47}],"hasCollect":false,"userAnswer":null,"questionPath":null},{"id":11564,"createTime":"2019-07-01 13:52:28","topicId":null,"tagId":930,"rule":1,"weight":1,"sort":327,"accuracy":0.0,"content":"<p><span style=\"font-family: 楷体;font-size: 16px\"><span style=\"font-family:楷体\">女，</span>18岁。晨起眼睑水肿3个月，查体：可见颜面、下肢水肿。尿常规：尿蛋白（++++），其水肿原因主要考虑为</span></p><p><br/></p>","trueCnt":0,"falseCnt":0,"analysis":"<p><span style=\"font-family: 楷体;font-size: 16px\"><span style=\"font-family:楷体\">解析：该患者尿液大量蛋白尿，存在低蛋白血症，水肿主要由血浆胶体渗透压降低引起。</span></span></p><p><br/></p>","topic":null,"options":[{"id":52006,"delFlag":false,"createTime":"2019-07-01 13:52:28","updateTime":"2019-07-01 13:52:28","isTrue":false,"questionId":11564,"content":"<p><span style=\"font-family: 楷体;font-size: 16px\"><span style=\"font-family:楷体\">毛细血管血压增高</span></span></p>","selectCnt":0},{"id":52007,"delFlag":false,"createTime":"2019-07-01 13:52:28","updateTime":"2019-07-01 13:52:28","isTrue":true,"questionId":11564,"content":"<p><span style=\"font-family: 楷体;font-size: 16px\"><span style=\"font-family:楷体\">血浆胶体渗透压降低</span></span></p>","selectCnt":0},{"id":52008,"delFlag":false,"createTime":"2019-07-01 13:52:28","updateTime":"2019-07-01 13:52:28","isTrue":false,"questionId":11564,"content":"<p><span style=\"font-family: 楷体;font-size: 16px\"><span style=\"font-family:楷体\">淋巴回流受阻</span></span></p>","selectCnt":0},{"id":52009,"delFlag":false,"createTime":"2019-07-01 13:52:28","updateTime":"2019-07-01 13:52:28","isTrue":false,"questionId":11564,"content":"<p><span style=\"font-family: 楷体;font-size: 16px\"><span style=\"font-family:楷体\">组织液静水压降低</span></span></p>","selectCnt":0},{"id":52010,"delFlag":false,"createTime":"2019-07-01 13:52:28","updateTime":"2019-07-01 13:52:28","isTrue":false,"questionId":11564,"content":"<p><span style=\"font-family: 楷体;font-size: 16px\"><span style=\"font-family:楷体\">组织液胶体渗透压升高</span></span></p>","selectCnt":0}],"tags":[{"id":930,"delFlag":false,"createTime":"2019-06-09 11:27:34","updateTime":"2019-06-09 11:27:34","name":"172","questionCnt":150,"tagTypeId":46},{"id":946,"delFlag":false,"createTime":"2019-06-09 11:31:57","updateTime":"2019-06-09 11:31:57","name":"泌尿A2","questionCnt":24,"tagTypeId":47}],"hasCollect":false,"userAnswer":null,"questionPath":null},{"id":11514,"createTime":"2019-07-01 12:02:31","topicId":null,"tagId":946,"rule":1,"weight":1,"sort":324,"accuracy":0.0,"content":"<p><span style=\"font-family: 楷体;font-size: 16px\"><span style=\"font-family:楷体\">男，</span>44岁。腹胀、乏力半年，加重伴尿量减少3天。尿量100-200ml/d。查体：P80次/分，R19次/分，慢性病容，口唇无发绀，可见蜘蛛痣，巩膜黄染。腹膨隆，无压痛及反跳痛，肝肋下未触及，脾平脐，移动性浊音（+），双下肢凹陷性水肿，实验室检查：WBC2.8×10</span><sup><span style=\"font-family: 楷体;font-size: 16px;vertical-align: super\">9</span></sup><span style=\"font-family: 楷体;font-size: 16px\">/L，N0.62，AbsAg(+),AST86U/L,ALT52U/L,TbiL46umol/L,BUN18.6mmol/L,SCr258.3umol/L。最有可能的诊断是</span></p><p><br/></p>","trueCnt":0,"falseCnt":0,"analysis":"<p><span style=\"font-family: 楷体;font-size: 16px\"><span style=\"font-family:楷体\">解析：肝肾综合征</span> <span style=\"font-family:楷体\">：其临床特征性表现为</span>&quot;三低一高&quot;，即自发性少尿或无尿、低尿钠、稀释性低血钠和氮质血症。肾脏本身无重要病理改变，故为功能性肾衰竭。其发病机制为肝硬化大量腹水等因素使机体有效循环血量不足，导致肾皮质血流量和肾小球滤过率持续降低。</span></p><p><br/></p>","topic":null,"options":[{"id":51757,"delFlag":true,"createTime":"2019-07-01 12:02:31","updateTime":"2019-07-01 12:02:31","isTrue":false,"questionId":11514,"content":"<p><span style=\"font-family: 楷体;font-size: 16px\"><span style=\"font-family:楷体\">自发性腹膜炎</span></span></p>","selectCnt":0},{"id":51758,"delFlag":true,"createTime":"2019-07-01 12:02:31","updateTime":"2019-07-01 12:02:31","isTrue":true,"questionId":11514,"content":"<p><span style=\"font-family: 楷体;font-size: 16px\"><span style=\"font-family:楷体\">肝肾综合征</span></span></p>","selectCnt":0},{"id":51759,"delFlag":false,"createTime":"2019-07-01 12:02:31","updateTime":"2019-07-01 12:02:31","isTrue":false,"questionId":11514,"content":"<p><span style=\"font-family: 楷体;font-size: 16px\"><span style=\"font-family:楷体\">肝肺综合征</span></span></p>","selectCnt":0},{"id":51760,"delFlag":true,"createTime":"2019-07-01 12:02:31","updateTime":"2019-07-01 12:02:31","isTrue":false,"questionId":11514,"content":"<p><span style=\"font-family: 楷体;font-size: 16px\"><span style=\"font-family:楷体\">肝性脑病</span></span></p>","selectCnt":0}],"tags":[{"id":930,"delFlag":false,"createTime":"2019-06-09 11:27:34","updateTime":"2019-06-09 11:27:34","name":"172","questionCnt":150,"tagTypeId":46},{"id":946,"delFlag":false,"createTime":"2019-06-09 11:31:57","updateTime":"2019-06-09 11:31:57","name":"泌尿A2","questionCnt":24,"tagTypeId":47}],"hasCollect":false,"userAnswer":null,"questionPath":null},{"id":11464,"createTime":"2019-07-01 11:38:18","topicId":null,"tagId":930,"rule":1,"weight":1,"sort":299,"accuracy":0.0,"content":"<p><span style=\"font-family: 楷体;font-size: 16px\"><span style=\"font-family:楷体\">男，</span>17岁。原发性肾病综合症，泼尼松60mg/天治疗，2周后尿蛋白转阴。最可能的肾脏病理类型是</span></p><p><br/></p>","trueCnt":0,"falseCnt":0,"analysis":"<p><span style=\"font-family: 楷体;font-size: 16px\"><span style=\"font-family:楷体\">解析：青少年</span>+原发性肾病综合征+激素敏感=微小病变型肾病。</span></p><p><br/></p>","topic":null,"options":[{"id":51507,"delFlag":false,"createTime":"2019-07-01 11:38:18","updateTime":"2019-07-01 11:38:18","isTrue":true,"questionId":11464,"content":"<p><span style=\"font-family: 楷体;font-size: 16px\"><span style=\"font-family:楷体\">微小病变型肾病</span></span></p>","selectCnt":0},{"id":51508,"delFlag":false,"createTime":"2019-07-01 11:38:18","updateTime":"2019-07-01 11:38:18","isTrue":false,"questionId":11464,"content":"<p><span style=\"font-family: 楷体;font-size: 16px\"><span style=\"font-family:楷体\">毛细血管内增生性肾小球肾炎</span></span></p>","selectCnt":0},{"id":51509,"delFlag":false,"createTime":"2019-07-01 11:38:18","updateTime":"2019-07-01 11:38:18","isTrue":false,"questionId":11464,"content":"<p><span style=\"font-family: 楷体;font-size: 16px\"><span style=\"font-family:楷体\">膜性肾病</span></span></p>","selectCnt":0},{"id":51510,"delFlag":false,"createTime":"2019-07-01 11:38:18","updateTime":"2019-07-01 11:38:18","isTrue":false,"questionId":11464,"content":"<p><span style=\"font-family: 楷体;font-size: 16px\">IgA肾病</span></p>","selectCnt":0},{"id":51511,"delFlag":false,"createTime":"2019-07-01 11:38:18","updateTime":"2019-07-01 11:38:18","isTrue":false,"questionId":11464,"content":"<p><span style=\"font-family: 楷体;font-size: 16px\"><span style=\"font-family:楷体\">膜增生性肾小球肾炎</span></span></p>","selectCnt":0}],"tags":[{"id":930,"delFlag":false,"createTime":"2019-06-09 11:27:34","updateTime":"2019-06-09 11:27:34","name":"172","questionCnt":150,"tagTypeId":46},{"id":946,"delFlag":false,"createTime":"2019-06-09 11:31:57","updateTime":"2019-06-09 11:31:57","name":"泌尿A2","questionCnt":24,"tagTypeId":47}],"hasCollect":false,"userAnswer":null,"questionPath":null},{"id":11282,"createTime":"2019-07-01 10:33:55","topicId":null,"tagId":928,"rule":1,"weight":1,"sort":101,"accuracy":0.0,"content":"<p><span style=\";font-family:楷体;font-size:16px\"><span style=\"font-family:楷体\">女，</span>28岁，咯血伴少尿3天。查体：T36.8℃, P74 次/分，BP160/100mmHg。 颜面及双下肢水肿，实验室检查：尿红细胞（++), 尿蛋白（++),尿素氮10. 5mmol/L。B超示双肾体积增大，该患者最可能的病理诊断是</span></p>","trueCnt":0,"falseCnt":0,"analysis":"<p><span style=\";font-family:楷体;font-size:16px\"><span style=\"font-family:楷体\">既有肾病又有咳血，考虑新月体性肾小球肾炎导致</span>Goodpasture综合征，故本题选B。Goodpasture 综合征由于肺泡壁毛细血管基膜和肾小球基底膜存在交叉反应抗原，故可以引起继发性肾损伤。</span></p>","topic":null,"options":[{"id":50597,"delFlag":false,"createTime":"2019-07-01 10:33:55","updateTime":"2019-07-01 10:33:55","isTrue":false,"questionId":11282,"content":"<p><span style=\";font-family:楷体;font-size:16px\"><span style=\"font-family:楷体\">慢性肾病</span></span></p>","selectCnt":0},{"id":50598,"delFlag":false,"createTime":"2019-07-01 10:33:55","updateTime":"2019-07-01 10:33:55","isTrue":true,"questionId":11282,"content":"<p><span style=\";font-family:楷体;font-size:16px\"><span style=\"font-family:楷体\">新月体性肾小球肾炎</span></span></p>","selectCnt":0},{"id":50599,"delFlag":false,"createTime":"2019-07-01 10:33:55","updateTime":"2019-07-01 10:33:55","isTrue":false,"questionId":11282,"content":"<p><span style=\";font-family:楷体;font-size:16px\"><span style=\"font-family:楷体\">急性肾盂肾炎</span></span></p>","selectCnt":0},{"id":50600,"delFlag":false,"createTime":"2019-07-01 10:33:55","updateTime":"2019-07-01 10:33:55","isTrue":false,"questionId":11282,"content":"<p><span style=\";font-family:楷体;font-size:16px\"><span style=\"font-family:楷体\">微小病变性肾病</span></span></p>","selectCnt":0},{"id":50601,"delFlag":false,"createTime":"2019-07-01 10:33:55","updateTime":"2019-07-01 10:33:55","isTrue":false,"questionId":11282,"content":"<p><span style=\";font-family:楷体;font-size:16px\"><span style=\"font-family:楷体\">系膜增生性肾小球肾炎</span></span></p>","selectCnt":0}],"tags":[{"id":928,"delFlag":false,"createTime":"2019-06-09 11:27:26","updateTime":"2019-06-09 11:27:26","name":"182","questionCnt":150,"tagTypeId":46},{"id":946,"delFlag":false,"createTime":"2019-06-09 11:31:57","updateTime":"2019-06-09 11:31:57","name":"泌尿A2","questionCnt":24,"tagTypeId":47}],"hasCollect":false,"userAnswer":null,"questionPath":null},{"id":11019,"createTime":"2019-06-29 17:04:34","topicId":null,"tagId":929,"rule":1,"weight":1,"sort":179,"accuracy":0.0,"content":"<p><span style=\";font-family:楷体;font-size:16px\"><span style=\"font-family:楷体\">女，</span>19岁。双下肢水肿3天。2周前患急性扁桃体炎，经口服抗生素后痊愈。查体：BP150/90mmhg，尿常规：蛋白（++），尿沉渣镜检红细胞10-20/高倍镜视野，血肌酐92umol/L，补体C</span><sub><span style=\";font-family:楷体;font-size:16px;vertical-align:sub\">3</span></sub><span style=\";font-family:楷体;font-size:16px\"><span style=\"font-family:楷体\">下降。最可能的发病机制为</span></span><span style=\";font-family:楷体;font-size:16px\"><br/></span></p><p><br/></p>","trueCnt":0,"falseCnt":0,"analysis":"<p><span style=\";font-family:楷体;font-size:16px\"><span style=\"font-family:楷体\">解析：急性肾小球肾炎是以急性肾炎综合征为主要临床表现的一组疾病。其特点为急性起病，患者出现血尿、蛋白尿、水肿和高血压，并可伴有一过性氮质血症。本病主要是由感染所诱发的免疫反应引起，链球菌的致病抗原</span>(至今未明)，通过循环免疫复合物或原位免疫复合物形成，诱发免疫炎症反应导致肾脏病变。</span></p><p><br/></p>","topic":null,"options":[{"id":49284,"delFlag":false,"createTime":"2019-06-29 17:04:34","updateTime":"2019-06-29 17:04:34","isTrue":false,"questionId":11019,"content":"<p><span style=\";font-family:楷体;font-size:16px\"><span style=\"font-family:楷体\">病毒直接对肾脏的破坏</span></span></p>","selectCnt":0},{"id":49285,"delFlag":false,"createTime":"2019-06-29 17:04:34","updateTime":"2019-06-29 17:04:34","isTrue":false,"questionId":11019,"content":"<p><span style=\";font-family:楷体;font-size:16px\"><span style=\"font-family:楷体\">细菌直接对肾脏的破坏</span></span></p>","selectCnt":0},{"id":49286,"delFlag":false,"createTime":"2019-06-29 17:04:34","updateTime":"2019-06-29 17:04:34","isTrue":true,"questionId":11019,"content":"<p><span style=\";font-family:楷体;font-size:16px\"><span style=\"font-family:楷体\">感染所致的免疫反应</span></span></p>","selectCnt":0},{"id":49287,"delFlag":false,"createTime":"2019-06-29 17:04:34","updateTime":"2019-06-29 17:04:34","isTrue":false,"questionId":11019,"content":"<p><span style=\";font-family:楷体;font-size:16px\"><span style=\"font-family:楷体\">机体代谢紊乱</span></span></p>","selectCnt":0},{"id":49288,"delFlag":false,"createTime":"2019-06-29 17:04:34","updateTime":"2019-06-29 17:04:34","isTrue":false,"questionId":11019,"content":"<p><span style=\";font-family:楷体;font-size:16px\"><span style=\"font-family:楷体\">感染所致的中毒反应</span></span></p>","selectCnt":0}],"tags":[{"id":929,"delFlag":false,"createTime":"2019-06-09 11:27:30","updateTime":"2019-06-09 11:27:30","name":"171","questionCnt":150,"tagTypeId":46},{"id":946,"delFlag":false,"createTime":"2019-06-09 11:31:57","updateTime":"2019-06-09 11:31:57","name":"泌尿A2","questionCnt":24,"tagTypeId":47}],"hasCollect":false,"userAnswer":null,"questionPath":null},{"id":11014,"createTime":"2019-06-29 16:58:17","topicId":null,"tagId":929,"rule":1,"weight":1,"sort":174,"accuracy":0.0,"content":"<p><span style=\";font-family:楷体;font-size:16px\"><span style=\"font-family:楷体\">男，</span>15岁。双下肢水肿2周。查体：眼睑轻度水肿，双下肢凹陷性水肿。尿常规：红细胞（-），蛋白（+++），尿蛋白定量4.8g/d，血浆白蛋白19g/L，肾穿刺活检示微小病变肾病。不恰当的治疗是</span></p><p><br/></p>","trueCnt":0,"falseCnt":0,"analysis":"<p><span style=\";font-family:楷体;font-size:16px\"><span style=\"font-family:楷体\">解析：患者无感染症状，预防性抗菌药物的应用对患者无益且可诱发真菌二重感染，故不宜应用。懒人</span></span><span style=\";font-family:楷体;font-size:16px\"><span style=\"font-family:楷体\">出品，必属精品</span></span><span style=\";font-family:楷体;font-size:16px\"><span style=\"font-family:楷体\">。</span></span></p><p><br/></p>","topic":null,"options":[{"id":49259,"delFlag":false,"createTime":"2019-06-29 16:58:17","updateTime":"2019-06-29 16:58:17","isTrue":true,"questionId":11014,"content":"<p><span style=\";font-family:楷体;font-size:16px\"><span style=\"font-family:楷体\">预防性应用抗生素</span></span></p>","selectCnt":0},{"id":49260,"delFlag":false,"createTime":"2019-06-29 16:58:17","updateTime":"2019-06-29 16:58:17","isTrue":false,"questionId":11014,"content":"<p><span style=\";font-family:楷体;font-size:16px\"><span style=\"font-family:楷体\">抗凝</span></span></p>","selectCnt":0},{"id":49261,"delFlag":false,"createTime":"2019-06-29 16:58:17","updateTime":"2019-06-29 16:58:17","isTrue":false,"questionId":11014,"content":"<p><span style=\";font-family:楷体;font-size:16px\"><span style=\"font-family:楷体\"></span></span></p><p><span style=\";font-family:楷体;font-size:16px\"><span style=\"font-family:楷体\">糖皮质激素</span></span></p><p></p>","selectCnt":0},{"id":49262,"delFlag":false,"createTime":"2019-06-29 16:58:17","updateTime":"2019-06-29 16:58:17","isTrue":false,"questionId":11014,"content":"<p><span style=\";font-family:楷体;font-size:16px\"><span style=\"font-family:楷体\">低盐低脂饮食</span></span></p>","selectCnt":0},{"id":49263,"delFlag":false,"createTime":"2019-06-29 16:58:17","updateTime":"2019-06-29 16:58:17","isTrue":false,"questionId":11014,"content":"<p><span style=\";font-family:楷体;font-size:16px\"><span style=\"font-family:楷体\">利尿剂</span></span></p>","selectCnt":0}],"tags":[{"id":929,"delFlag":false,"createTime":"2019-06-09 11:27:30","updateTime":"2019-06-09 11:27:30","name":"171","questionCnt":150,"tagTypeId":46},{"id":946,"delFlag":false,"createTime":"2019-06-09 11:31:57","updateTime":"2019-06-09 11:31:57","name":"泌尿A2","questionCnt":24,"tagTypeId":47}],"hasCollect":false,"userAnswer":null,"questionPath":null},{"id":11010,"createTime":"2019-06-29 16:56:03","topicId":null,"tagId":929,"rule":1,"weight":1,"sort":172,"accuracy":0.0,"content":"<p><span style=\";font-family:楷体;font-size:16px\"><span style=\"font-family:楷体\">男，</span>46岁。反复左腰部胀痛6个月，疼痛加重伴高热1周，经抗炎治疗后症状无缓解。左腰部触痛明显。既往有左肾绞痛、血尿病史。血常规WBC11.2×10</span><sup><span style=\";font-family:楷体;font-size:16px;vertical-align:super\">9</span></sup><span style=\";font-family:楷体;font-size:16px\">/L，N0.80。尿常规WBC（++++）。B超和KUB检查提示左输尿管上段结石，长径1.5cm，平第四腰椎横突，左肾重度积水。首选的治疗方法是</span></p><p><br/></p>","trueCnt":0,"falseCnt":0,"analysis":"<p><span style=\";font-family:楷体;font-size:16px\"><span style=\"font-family:楷体\">解析：肾功能极差，梗阻严重、全身情况差，应先行肾造瘘引流尿液，改善和恢复肾功能，待情况好转后再处理结石。懒人</span></span><span style=\";font-family:楷体;font-size:16px\"><span style=\"font-family:楷体\">出品，必属精品</span></span><span style=\";font-family:楷体;font-size:16px\"><span style=\"font-family:楷体\">。</span></span></p><p><br/></p>","topic":null,"options":[{"id":49239,"delFlag":false,"createTime":"2019-06-29 16:56:03","updateTime":"2019-06-29 16:56:03","isTrue":false,"questionId":11010,"content":"<p><span style=\";font-family:楷体;font-size:16px\"><span style=\"font-family:楷体\">输尿管切开取石</span></span></p>","selectCnt":0},{"id":49240,"delFlag":false,"createTime":"2019-06-29 16:56:03","updateTime":"2019-06-29 16:56:03","isTrue":false,"questionId":11010,"content":"<p><span style=\";font-family:楷体;font-size:16px\"><span style=\"font-family:楷体\">经皮肾镜碎石取石</span></span></p>","selectCnt":0},{"id":49241,"delFlag":false,"createTime":"2019-06-29 16:56:03","updateTime":"2019-06-29 16:56:03","isTrue":false,"questionId":11010,"content":"<p><span style=\";font-family:楷体;font-size:16px\"><span style=\"font-family:楷体\">体外冲击波碎石</span></span></p>","selectCnt":0},{"id":49242,"delFlag":false,"createTime":"2019-06-29 16:56:03","updateTime":"2019-06-29 16:56:03","isTrue":true,"questionId":11010,"content":"<p><span style=\";font-family:楷体;font-size:16px\"><span style=\"font-family:楷体\">肾穿刺造瘘</span></span></p>","selectCnt":0},{"id":49243,"delFlag":false,"createTime":"2019-06-29 16:56:03","updateTime":"2019-06-29 16:56:03","isTrue":false,"questionId":11010,"content":"<p><span style=\";font-family:楷体;font-size:16px\"><span style=\"font-family:楷体\">输尿管镜碎石取石</span></span></p>","selectCnt":0}],"tags":[{"id":929,"delFlag":false,"createTime":"2019-06-09 11:27:30","updateTime":"2019-06-09 11:27:30","name":"171","questionCnt":150,"tagTypeId":46},{"id":946,"delFlag":false,"createTime":"2019-06-09 11:31:57","updateTime":"2019-06-09 11:31:57","name":"泌尿A2","questionCnt":24,"tagTypeId":47}],"hasCollect":false,"userAnswer":null,"questionPath":null},{"id":11002,"createTime":"2019-06-29 16:53:52","topicId":null,"tagId":929,"rule":1,"weight":1,"sort":170,"accuracy":0.0,"content":"<p><span style=\";font-family:楷体;font-size:16px\"><span style=\"font-family:楷体\">男，</span>62岁。体检发现蛋白尿4个月。既往糖尿病病史8年，2年前因糖尿病视网膜病变行激光治疗。高血压病史5年。查体：BP150/80mmhg，双下肢轻度凹陷性水肿。尿常规：蛋白（++），红细胞（-）。尿蛋白定量2.6g/d。该患者蛋白尿的分类首先考虑为</span></p><p><br/></p>","trueCnt":0,"falseCnt":0,"analysis":"<p><span style=\";font-family:楷体;font-size:16px\"><span style=\"font-family:楷体\">解析：根据肾小球性蛋白尿的选择性可分为选择性蛋白尿和非选择性蛋白尿，前者以白蛋白为主，并有少量的小分子量蛋白</span>(如</span><span style=\";font-family:Calibri;font-size:16px\">ß</span><span style=\";font-family:楷体;font-size:16px\">z-MG)，无大分子量的蛋白，见于微小病变肾病和早期糖尿病肾病。该患者有糖尿病，所以答案为肾小球性蛋白尿。懒人</span><span style=\";font-family:楷体;font-size:16px\"><span style=\"font-family:楷体\">出品，必属精品</span></span><span style=\";font-family:楷体;font-size:16px\"><span style=\"font-family:楷体\">。</span></span></p><p><br/></p>","topic":null,"options":[{"id":49199,"delFlag":false,"createTime":"2019-06-29 16:53:52","updateTime":"2019-06-29 16:53:52","isTrue":false,"questionId":11002,"content":"<p><span style=\";font-family:楷体;font-size:16px\"><span style=\"font-family:楷体\">溢出性蛋白尿</span></span></p>","selectCnt":0},{"id":49200,"delFlag":false,"createTime":"2019-06-29 16:53:52","updateTime":"2019-06-29 16:53:52","isTrue":false,"questionId":11002,"content":"<p><span style=\";font-family:楷体;font-size:16px\"><span style=\"font-family:楷体\">分泌性蛋白尿</span></span></p>","selectCnt":0},{"id":49201,"delFlag":false,"createTime":"2019-06-29 16:53:52","updateTime":"2019-06-29 16:53:52","isTrue":true,"questionId":11002,"content":"<p><span style=\";font-family:楷体;font-size:16px\"><span style=\"font-family:楷体\">肾小球性蛋白尿</span></span></p>","selectCnt":0},{"id":49202,"delFlag":false,"createTime":"2019-06-29 16:53:52","updateTime":"2019-06-29 16:53:52","isTrue":false,"questionId":11002,"content":"<p><span style=\";font-family:楷体;font-size:16px\"><span style=\"font-family:楷体\">组织性蛋白尿</span></span></p>","selectCnt":0},{"id":49203,"delFlag":false,"createTime":"2019-06-29 16:53:52","updateTime":"2019-06-29 16:53:52","isTrue":false,"questionId":11002,"content":"<p><span style=\";font-family:楷体;font-size:16px\"><span style=\"font-family:楷体\">肾小管性蛋白尿</span></span></p>","selectCnt":0}],"tags":[{"id":929,"delFlag":false,"createTime":"2019-06-09 11:27:30","updateTime":"2019-06-09 11:27:30","name":"171","questionCnt":150,"tagTypeId":46},{"id":946,"delFlag":false,"createTime":"2019-06-09 11:31:57","updateTime":"2019-06-09 11:31:57","name":"泌尿A2","questionCnt":24,"tagTypeId":47}],"hasCollect":false,"userAnswer":null,"questionPath":null},{"id":2468,"createTime":"2019-06-20 10:20:50","topicId":null,"tagId":927,"rule":1,"weight":1,"sort":107,"accuracy":0.0,"content":"<p><span style=\";font-family:楷体;font-size:16px\"><span style=\"font-family:楷体\">女，</span>65岁。间歇全程肉眼血尿2个月，尿呈洗肉水样。无尿频、尿急、尿痛。间断出现，近日血尿加重。配偶吸烟。最可能的疾病是</span></p>","trueCnt":0,"falseCnt":0,"analysis":"<p><span style=\";font-family:楷体;font-size:16px\">①</span><span style=\";font-family:楷体;font-size:16px\"><span style=\"font-family:楷体\">膀胱癌</span>:血尿是膀胱癌最常见和最早出现的症状。约85%的病人表现为间歇性肉眼血尿,可自行减轻或停止，易给病人造成“好转”或“治愈”的错觉而贻误治疗。然而，有时可仅为显微镜下血尿。出血量多少与肿瘤大小、数目及恶性程度并不一致。非上皮性肿瘤血尿一般较轻。尿频、尿急、尿痛亦是常见的症状，多为膀胱肿瘤的晚期表现,常因肿瘤坏死、溃疡或并发感染所致。少数广泛原位癌或浸润性癌起始即有膀胱刺激症状,预后不良。有时尿内混有“腐肉”样坏死组织排出;三角区及膀胱颈部肿瘤可梗阻膀胱出口,造成排尿困难,甚至尿潴留。 ②膀胱炎：膀胱炎占尿路感染的60%以上，分为急性单纯性膀胱炎和反复发作性膀胱炎。主要表现为尿频、尿急、尿痛、排尿不适、下腹部疼痛等,部分患者迅速出现排尿困难。尿液常混浊,并有异味,约30%可出现血尿。一般无全身感染症状,少数患者出现腰痛、发热，但体温常不超过38℃。如患者有突出的全身表现，体温＞38.℃ ,应考虑上尿路感染。致病菌多为大肠埃希菌，约占75%以上。③肾盂肾炎：急性肾盂肾炎 ： 可发生于各年龄段，育龄女性最多见。临床表现与感染程度有关,通常起病较急。全身症状:发热、寒战、头痛、全身酸痛、恶心、呕吐等，体温多在38.0 ℃以上,多为弛张热，也可呈稽留热或间歇热。部分患者出现革兰阴性杆菌败血症。泌尿系统症状:尿频、尿急、尿痛、排尿困难、下腹部疼痛、腰痛等。腰痛程度不一，多为钝痛或酸痛。部分患者膀胱刺激症状不典型或缺如。体格检查:除发热、心动过速和全身肌肉压痛外，还可发现一侧或两侧肋脊角或输尿管点压痛和(或)肾区叩击痛。④尿路结石：尿道结石典型症状为排尿困难,点滴状排尿，伴尿痛，重者可发生急性尿潴留及会阴部剧痛。除典型症状外，下尿路结石常伴发血尿和感染。憩室内结石可仅表现为尿路感染。⑤肾癌：肾癌临床表现多种多样,亦可全无症状。血尿、疼痛和肿块是肾癌的主要症状,出现其中任何一项或两项症状，即应考虑肾癌的可能。</span></p>","topic":null,"options":[{"id":6627,"delFlag":false,"createTime":"2019-06-20 10:20:50","updateTime":"2019-06-20 10:20:50","isTrue":true,"questionId":2468,"content":"<p><span style=\";font-family:楷体;font-size:16px\"><span style=\"font-family:楷体\">膀胱癌</span></span></p>","selectCnt":0},{"id":6628,"delFlag":false,"createTime":"2019-06-20 10:20:50","updateTime":"2019-06-20 10:20:50","isTrue":false,"questionId":2468,"content":"<p><span style=\";font-family:楷体;font-size:16px\"><span style=\"font-family:楷体\">膀胱炎</span></span></p>","selectCnt":0},{"id":6629,"delFlag":false,"createTime":"2019-06-20 10:20:50","updateTime":"2019-06-20 10:20:50","isTrue":false,"questionId":2468,"content":"<p><span style=\";font-family:楷体;font-size:16px\"><span style=\"font-family:楷体\">肾盂肾炎</span></span></p>","selectCnt":0},{"id":6630,"delFlag":false,"createTime":"2019-06-20 10:20:50","updateTime":"2019-06-20 10:20:50","isTrue":false,"questionId":2468,"content":"<p><span style=\";font-family:楷体;font-size:16px\"><span style=\"font-family:楷体\">尿路结石</span></span></p>","selectCnt":0},{"id":6631,"delFlag":false,"createTime":"2019-06-20 10:20:50","updateTime":"2019-06-20 10:20:50","isTrue":false,"questionId":2468,"content":"<p><span style=\";font-family:楷体;font-size:16px\"><span style=\"font-family:楷体\">肾癌</span></span></p>","selectCnt":0}],"tags":[{"id":927,"delFlag":false,"createTime":"2019-06-09 11:27:22","updateTime":"2019-06-09 11:27:22","name":"181","questionCnt":150,"tagTypeId":46},{"id":946,"delFlag":false,"createTime":"2019-06-09 11:31:57","updateTime":"2019-06-09 11:31:57","name":"泌尿A2","questionCnt":24,"tagTypeId":47}],"hasCollect":false,"userAnswer":null,"questionPath":null},{"id":2404,"createTime":"2019-06-20 09:49:23","topicId":null,"tagId":927,"rule":1,"weight":1,"sort":99,"accuracy":0.0,"content":"<p><span style=\";font-family:楷体;font-size:16px\"><span style=\"font-family:楷体\">男，</span>18岁。进行性全身水肿1周，无发热、皮疹及关节痛。查体：BP110/70mmHg,面及双下肢重度凹陷性水肿，移动性浊音(+)。尿沉渣镜检:RBC0-2/HP。尿蛋白定量5.6g/d,血肌酐684mo1/L,白蛋白21g/L,乙型肝炎病毒标志物阴性。该患者最可能的肾脏病理诊断为</span></p>","trueCnt":0,"falseCnt":0,"analysis":"<p><span style=\";font-family:楷体;font-size:16px\"><span style=\"font-family:楷体\">微小病变型肾病：本病多见于儿童。可发生于呼吸道感染或免疫接种之后。临床主要表现为肾病综合征。水肿常为最早出现的症状。蛋白尿多为选择性。通常不出现高血压或血尿。皮质类固醇治疗对</span>90%以上的儿童患者有明显疗效,部分患者病情复发,有的甚至出现皮质类固醇依赖或抵抗现象,但远期预后较好，患儿至青春期病情常可缓解。成人患者对皮质类固醇治疗反应缓慢或疗效不明显。</span></p><p><span style=\";font-family:楷体;font-size:16px\"><span style=\"font-family:楷体\">（</span>1）膜增生性肾小球肾炎：本病多发生于儿童和青年,主要表现为肾病综合征,常伴有血尿，也可仅表现为蛋白尿。本病常为慢性进展性,预后较差。伴有大量新月体形成的患者出现急进性肾炎的临床表现。约50%的患者在10年内出现慢性肾衰竭。激素和免疫抑制剂治疗的效果常不明显。肾移植后病变常复发。致密沉积物病的复发率较高。</span></p><p><span style=\";font-family:楷体;font-size:16px\"><span style=\"font-family:楷体\">（</span>2）毛细血管内增生性肾炎：急性肾炎多见于儿童，主要表现为急性肾炎综合征。通常于咽部等处感染后10天左右出现发热、少尿和血尿等症状。血尿为常见症状,约有30%的患者出现肉眼血尿，多数患者出现镜下血尿。尿中可出现各种管型，可有轻度蛋白尿(通常低于1g/d)。患者常出现水肿和轻到中度高血压。水肿的主要原因是肾小球滤过率降低,水、钠潴留、超敏反应引起的毛细血管通透性增高可使水肿加重。高血压的原因可能是钠、水潴留,血容量增加。血浆肾素水平一般不增高。成人患者的症状不典型,可表现为高血压和水肿，常伴有血尿素氨增高。</span></p><p><span style=\";font-family:楷体;font-size:16px\"><span style=\"font-family:楷体\">（</span>3）膜性肾病：膜性肾小球病多见于成人。临床常表现为肾病综合征。 &nbsp;由于肾小球基膜严重损伤，滤过膜通透性明显增高，常表现为非选择性蛋白尿。约15%的患者表现为非肾病综合征性蛋白尿。部分患者伴有血尿或轻度高血压。</span></p><p><span style=\";font-family:楷体;font-size:16px\"><span style=\"font-family:楷体\">（</span>4）IgA肾病：IgA肾病可发生于不同年龄的个体,儿童和青年多发。发病前常有，上呼吸道感染,少数发生于胃肠道或尿路感染后。30%-40%的患者仅出现镜下血尿,可伴有轻度蛋白尿。5%~10%的患者表现为急性肾炎综合征。血尿通常持续数天,以后消失,但每隔数月复发。本病预后差异很大,许多患者肾功能可长期维持正常,但15%~40%的患者病情缓慢进展,在20</span></p><p><span style=\";font-family:楷体;font-size:16px\"><span style=\"font-family:楷体\">年内发生慢性肾衰竭。发病年龄大、出现大量蛋白尿、高血压或肾活检时发现血管硬化或新月体形成者预后较差。肾移植后可重新出现</span>IgA沉积，并引起相应的临床改变。</span></p>","topic":null,"options":[{"id":6307,"delFlag":false,"createTime":"2019-06-20 09:49:23","updateTime":"2019-06-20 09:49:23","isTrue":false,"questionId":2404,"content":"<p><span style=\";font-family:楷体;font-size:16px\"><span style=\"font-family:楷体\">膜增生性肾小球肾炎</span></span></p>","selectCnt":0},{"id":6308,"delFlag":false,"createTime":"2019-06-20 09:49:23","updateTime":"2019-06-20 09:49:23","isTrue":false,"questionId":2404,"content":"<p><span style=\";font-family:楷体;font-size:16px\"><span style=\"font-family:楷体\">毛细血管内增生性肾炎</span></span></p>","selectCnt":0},{"id":6309,"delFlag":false,"createTime":"2019-06-20 09:49:23","updateTime":"2019-06-20 09:49:23","isTrue":false,"questionId":2404,"content":"<p><span style=\";font-family:楷体;font-size:16px\"><span style=\"font-family:楷体\">膜性肾病</span></span></p>","selectCnt":0},{"id":6310,"delFlag":false,"createTime":"2019-06-20 09:49:23","updateTime":"2019-06-20 09:49:23","isTrue":true,"questionId":2404,"content":"<p><span style=\";font-family:楷体;font-size:16px\"><span style=\"font-family:楷体\">微小病变型肾病</span></span></p>","selectCnt":0},{"id":6311,"delFlag":false,"createTime":"2019-06-20 09:49:23","updateTime":"2019-06-20 09:49:23","isTrue":false,"questionId":2404,"content":"<p><span style=\";font-family:楷体;font-size:16px\">IgA肾病</span></p>","selectCnt":0}],"tags":[{"id":927,"delFlag":false,"createTime":"2019-06-09 11:27:22","updateTime":"2019-06-09 11:27:22","name":"181","questionCnt":150,"tagTypeId":46},{"id":946,"delFlag":false,"createTime":"2019-06-09 11:31:57","updateTime":"2019-06-09 11:31:57","name":"泌尿A2","questionCnt":24,"tagTypeId":47}],"hasCollect":false,"userAnswer":null,"questionPath":null},{"id":2388,"createTime":"2019-06-20 09:42:50","topicId":null,"tagId":927,"rule":1,"weight":1,"sort":95,"accuracy":0.0,"content":"<p><span style=\";font-family:楷体;font-size:16px\"><span style=\"font-family:楷体\">男，</span>45岁。发现血尿、蛋白尿8年。查体:BP150/90mmHg。实验室检查:尿蛋白定量1.2-1.8g/d，血肌酐110umo1/L。临床诊断是</span></p>","trueCnt":0,"falseCnt":0,"analysis":"<p><span style=\";font-family:楷体;font-size:16px\"><span style=\"font-family:楷体\">既往肾炎史不详，无明显前期感染</span>,除有肾炎症状外,常有贫血、肾功能异常、低比重尿或固定低比重尿，尿改变以蛋白增多为主。（1）急性肾炎的典型表现：前驱感染后急性起病，水肿、血尿、蛋白尿、高血压、尿量减少。（2）肾病综合征诊断标</span><span style=\";font-family:楷体;font-size:16px\"><span style=\"font-family:楷体\">准是</span>:①尿蛋白大于3.5g/d;②血浆白蛋白低于30g/L;③水肿;④血脂升高。其中①②两项为诊断所必需</span><span style=\";font-family:楷体;letter-spacing:0;font-size:16px\"><span style=\"font-family:楷体\">。</span></span><span style=\";font-family:楷体;font-size:16px\"><span style=\"font-family:楷体\">（</span>3）无症状性血尿或(和)蛋白尿既往国内称为隐匿型肾小球肾炎，系指无水肿、高血压及肾功能损害,而仅表现为肾小球源性血尿或(和)蛋白尿的一组肾小球疾病。</span><span style=\";font-family:楷体;font-size:16px\"><span style=\"font-family:楷体\">（</span>4）</span><span style=\";font-family:楷体;font-size:16px\"><span style=\"font-family:楷体\">长期持续高血压使肾小球内囊压力升高</span>,肾小球纤维化、萎缩，肾动脉硬化，导致肾实质缺血和肾单位不断减少。慢性肾衰竭是长期高血压的严重后果之一,尤其在合并糖尿病时。恶性高血压时，入球小动脉及小叶间动脉发生增殖性内膜炎及纤维素样坏死,可在短期内出现肾衰竭。</span></p>","topic":null,"options":[{"id":6227,"delFlag":false,"createTime":"2019-06-20 09:42:50","updateTime":"2019-06-20 09:42:50","isTrue":false,"questionId":2388,"content":"<p><span style=\";font-family:楷体;font-size:16px\"><span style=\"font-family:楷体\">急性肾小球肾炎</span></span></p>","selectCnt":0},{"id":6228,"delFlag":false,"createTime":"2019-06-20 09:42:50","updateTime":"2019-06-20 09:42:50","isTrue":false,"questionId":2388,"content":"<p><span style=\";font-family:楷体;font-size:16px\"><span style=\"font-family:楷体\">肾病综合征</span></span></p>","selectCnt":0},{"id":6229,"delFlag":false,"createTime":"2019-06-20 09:42:50","updateTime":"2019-06-20 09:42:50","isTrue":false,"questionId":2388,"content":"<p><span style=\";font-family:楷体;font-size:16px\"><span style=\"font-family:楷体\">隐匿型肾小球肾炎</span></span></p>","selectCnt":0},{"id":6230,"delFlag":false,"createTime":"2019-06-20 09:42:50","updateTime":"2019-06-20 09:42:50","isTrue":false,"questionId":2388,"content":"<p><span style=\";font-family:楷体;font-size:16px\"><span style=\"font-family:楷体\">高血压肾损害</span></span></p>","selectCnt":0},{"id":6231,"delFlag":false,"createTime":"2019-06-20 09:42:50","updateTime":"2019-06-20 09:42:50","isTrue":true,"questionId":2388,"content":"<p><span style=\";font-family:楷体;font-size:16px\"><span style=\"font-family:楷体\">慢性肾小球肾炎</span></span></p>","selectCnt":0}],"tags":[{"id":927,"delFlag":false,"createTime":"2019-06-09 11:27:22","updateTime":"2019-06-09 11:27:22","name":"181","questionCnt":150,"tagTypeId":46},{"id":946,"delFlag":false,"createTime":"2019-06-09 11:31:57","updateTime":"2019-06-09 11:31:57","name":"泌尿A2","questionCnt":24,"tagTypeId":47}],"hasCollect":false,"userAnswer":null,"questionPath":null},{"id":2335,"createTime":"2019-06-20 09:21:13","topicId":null,"tagId":927,"rule":1,"weight":1,"sort":82,"accuracy":0.0,"content":"<p><span style=\";font-family:楷体;font-size:16px\"><span style=\"font-family:楷体\">男，</span>35岁。B超发现右输尿管上段结石，大小1.2cm×0.8cm,合并轻度右肾积水。无发热，静脉尿路造影(IVU)显示右输尿管上段结石，右肾轻度积水，输尿管显影。首选的治疗方法是</span></p>","trueCnt":0,"falseCnt":0,"analysis":"<p><span style=\";font-family:楷体;font-size:16px\"><span style=\"font-family:楷体\">药物排石治疗：结石＜</span>0.6cm、表面光滑,结石以下尿路无梗阻时可采用药物排石治疗。体外冲击波碎石：</span><span style=\";font-family:楷体;font-size:16px\"><span style=\"font-family:楷体\">适应证</span>:适用于直径≤2cm的肾结石及输尿管上段结石。输尿管中下段结石治疗的成功率比输尿管镜取石低。</span><span style=\";font-family:楷体;font-size:16px\"><span style=\"font-family:楷体\">经皮肾镜碎石取石：适用于所有需开放手术干预的肾结石</span>,包括完全性和不完全性鹿角结石、≥2cm的肾结石,有症状的肾盏或憩室内结石、体外冲击波难以粉碎及治疗失败的结石,以及部分L</span><sub><span style=\";font-family:楷体;font-size:16px;vertical-align:sub\">4</span></sub><span style=\";font-family:楷体;font-size:16px\"><span style=\"font-family:楷体\">以上较大的输尿管上段结石。输尿管镜碎石取石：主要用于肾结石</span>(＜2cm)的治疗。开放输尿管切开取石：适用于嵌顿较久或其他的方法治疗无效的结石。手术径路需根据结石部位选定。腹腔镜输尿管切开取石：适用于输尿管结石＞2cm,原来考虑开放手术;或经ESWL、输尿管镜手术治疗失败者。</span></p>","topic":null,"options":[{"id":5962,"delFlag":false,"createTime":"2019-06-20 09:21:13","updateTime":"2019-06-20 09:21:13","isTrue":true,"questionId":2335,"content":"<p><span style=\";font-family:楷体;font-size:16px\"><span style=\"font-family:楷体\">体外冲击波碎石</span></span></p>","selectCnt":0},{"id":5963,"delFlag":false,"createTime":"2019-06-20 09:21:13","updateTime":"2019-06-20 09:21:13","isTrue":false,"questionId":2335,"content":"<p><span style=\";font-family:楷体;font-size:16px\"><span style=\"font-family:楷体\">输尿管镜碎石取石</span></span></p>","selectCnt":0},{"id":5964,"delFlag":false,"createTime":"2019-06-20 09:21:13","updateTime":"2019-06-20 09:21:13","isTrue":false,"questionId":2335,"content":"<p><span style=\";font-family:楷体;font-size:16px\"><span style=\"font-family:楷体\">经皮肾镜碎石取石</span></span></p>","selectCnt":0},{"id":5965,"delFlag":false,"createTime":"2019-06-20 09:21:13","updateTime":"2019-06-20 09:21:13","isTrue":false,"questionId":2335,"content":"<p><span style=\";font-family:楷体;font-size:16px\"><span style=\"font-family:楷体\">开放输尿管切开取石</span></span></p>","selectCnt":0},{"id":5966,"delFlag":false,"createTime":"2019-06-20 09:21:13","updateTime":"2019-06-20 09:21:13","isTrue":false,"questionId":2335,"content":"<p><span style=\";font-family:楷体;font-size:16px\"><span style=\"font-family:楷体\">腹腔镜输尿管切开取石</span></span></p>","selectCnt":0}],"tags":[{"id":927,"delFlag":false,"createTime":"2019-06-09 11:27:22","updateTime":"2019-06-09 11:27:22","name":"181","questionCnt":150,"tagTypeId":46},{"id":946,"delFlag":false,"createTime":"2019-06-09 11:31:57","updateTime":"2019-06-09 11:31:57","name":"泌尿A2","questionCnt":24,"tagTypeId":47}],"hasCollect":false,"userAnswer":null,"questionPath":null},{"id":2291,"createTime":"2019-06-20 09:00:17","topicId":null,"tagId":927,"rule":1,"weight":1,"sort":70,"accuracy":0.0,"content":"<p><span style=\";font-family:楷体;font-size:16px\"><span style=\"font-family:楷体\">男，</span>65岁。进行性排尿困难2年，不能自行排尿2小时，膀胱膨隆，轻压痛。首选的治疗方法应是</span></p>","trueCnt":0,"falseCnt":0,"analysis":"<p><span style=\";font-family:楷体;font-size:16px\"><span style=\"font-family:楷体\">老年男性，表现为进行性排尿困难，考虑诊断为前列腺增生。前列腺增生患者目前出现疾病的尿潴留，最常用的方法是导尿术。如果导尿术失败，可行耻骨上膀胱穿刺抽吸术或者造瘘术。</span>③药物治疗为一般的保守治疗，不能缓解症状。</span></p>","topic":null,"options":[{"id":5743,"delFlag":false,"createTime":"2019-06-20 09:00:17","updateTime":"2019-06-20 09:00:17","isTrue":true,"questionId":2291,"content":"<p><span style=\";font-family:楷体;font-size:16px\"><span style=\"font-family:楷体\">导尿并保留导尿管</span></span></p>","selectCnt":0},{"id":5744,"delFlag":false,"createTime":"2019-06-20 09:00:17","updateTime":"2019-06-20 09:00:17","isTrue":false,"questionId":2291,"content":"<p><span style=\";font-family:楷体;font-size:16px\"><span style=\"font-family:楷体\">药物治疗</span></span></p>","selectCnt":0},{"id":5745,"delFlag":false,"createTime":"2019-06-20 09:00:17","updateTime":"2019-06-20 09:00:17","isTrue":false,"questionId":2291,"content":"<p><span style=\";font-family:楷体;font-size:16px\"><span style=\"font-family:楷体\">耻骨上膀胱穿刺</span></span></p>","selectCnt":0},{"id":5746,"delFlag":false,"createTime":"2019-06-20 09:00:17","updateTime":"2019-06-20 09:00:17","isTrue":false,"questionId":2291,"content":"<p><span style=\";font-family:楷体;font-size:16px\"><span style=\"font-family:楷体\">耻骨上膀胱造瘘</span></span></p>","selectCnt":0},{"id":5747,"delFlag":false,"createTime":"2019-06-20 09:00:17","updateTime":"2019-06-20 09:00:17","isTrue":false,"questionId":2291,"content":"<p><span style=\";font-family:楷体;font-size:16px\"><span style=\"font-family:楷体\">针灸</span></span></p>","selectCnt":0}],"tags":[{"id":927,"delFlag":false,"createTime":"2019-06-09 11:27:22","updateTime":"2019-06-09 11:27:22","name":"181","questionCnt":150,"tagTypeId":46},{"id":946,"delFlag":false,"createTime":"2019-06-09 11:31:57","updateTime":"2019-06-09 11:31:57","name":"泌尿A2","questionCnt":24,"tagTypeId":47}],"hasCollect":false,"userAnswer":null,"questionPath":null},{"id":2284,"createTime":"2019-06-20 08:55:28","topicId":null,"tagId":927,"rule":1,"weight":1,"sort":67,"accuracy":0.0,"content":"<p><span style=\";font-family:楷体;font-size:16px\"><span style=\"font-family:楷体\">女，</span>28岁，尿急，尿频，尿痛2天，查体: T36.5℃，双肾区无叩痛，尿沉渣镜检:RBC5-10/HP,WBC20-30/HP, 最可能的诊断为</span></p>","trueCnt":0,"falseCnt":0,"analysis":"<p><span style=\";font-family:楷体;font-size:16px\"><span style=\"font-family:楷体\">青年女性，出现尿频、尿急、尿痛</span>+双肾区无叩击痛+尿WBC20-30/HP, RBC5- 10/HP,考虑急性膀胱炎，故本题选A。②急性肾孟肾炎除了有膀胱刺激征以外，多有肾区叩击痛。③急性肾小球肾炎、急进性肾小球肾炎主要表现为血尿及蛋白尿，无膀胱刺激症状。④急性间质性肾炎：急性间质性肾炎常同时具有全身过敏表现，可表现为皮疹、发热及外周血嗜酸性白细胞计数增多。</span></p>","topic":null,"options":[{"id":5708,"delFlag":false,"createTime":"2019-06-20 08:55:28","updateTime":"2019-06-20 08:55:28","isTrue":true,"questionId":2284,"content":"<p><span style=\";font-family:楷体;font-size:16px\"><span style=\"font-family:楷体\">急性膀胱炎</span></span></p>","selectCnt":0},{"id":5709,"delFlag":false,"createTime":"2019-06-20 08:55:28","updateTime":"2019-06-20 08:55:28","isTrue":false,"questionId":2284,"content":"<p><span style=\";font-family:楷体;font-size:16px\"><span style=\"font-family:楷体\">急进性肾小球肾炎</span></span></p>","selectCnt":0},{"id":5710,"delFlag":false,"createTime":"2019-06-20 08:55:28","updateTime":"2019-06-20 08:55:28","isTrue":false,"questionId":2284,"content":"<p><span style=\";font-family:楷体;font-size:16px\"><span style=\"font-family:楷体\">急性间质性肾炎</span></span></p>","selectCnt":0},{"id":5711,"delFlag":false,"createTime":"2019-06-20 08:55:28","updateTime":"2019-06-20 08:55:28","isTrue":false,"questionId":2284,"content":"<p><span style=\";font-family:楷体;font-size:16px\"><span style=\"font-family:楷体\">急性肾小球肾炎</span></span></p>","selectCnt":0},{"id":5712,"delFlag":false,"createTime":"2019-06-20 08:55:28","updateTime":"2019-06-20 08:55:28","isTrue":false,"questionId":2284,"content":"<p><span style=\";font-family:楷体;font-size:16px\"><span style=\"font-family:楷体\">急性肾孟肾炎</span></span></p>","selectCnt":0}],"tags":[{"id":927,"delFlag":false,"createTime":"2019-06-09 11:27:22","updateTime":"2019-06-09 11:27:22","name":"181","questionCnt":150,"tagTypeId":46},{"id":946,"delFlag":false,"createTime":"2019-06-09 11:31:57","updateTime":"2019-06-09 11:31:57","name":"泌尿A2","questionCnt":24,"tagTypeId":47}],"hasCollect":false,"userAnswer":null,"questionPath":null},{"id":2248,"createTime":"2019-06-19 17:52:21","topicId":null,"tagId":927,"rule":1,"weight":1,"sort":57,"accuracy":0.0,"content":"<p><span style=\";font-family:楷体;font-size:16px\"><span style=\"font-family:楷体\">女，</span>56岁，间断水肿8年，加重伴头痛、恶心10天，查体: T 36.5℃，P110 次/分，BP100/70mmHg， 贫血貌，双中下肺可闻及湿啰音，双下肢中度凹陷性水肿。尿常规:蛋白(</span><span style=\";font-family:楷体;font-size:16px\">++</span><span style=\";font-family:楷体;font-size:16px\">+)，尿沉渣镜检RBC 10</span><span style=\";font-family:楷体;font-size:16px\">-</span><span style=\";font-family:楷体;font-size:16px\">15/HP， 血红蛋白68g/L,血肌酐892μmo1/L, 钾6.2mmo1/L,二氧化碳结合力10mmol/L。该患者最重要的治疗为</span></p>","trueCnt":0,"falseCnt":0,"analysis":"<p><span style=\";font-family:楷体;font-size:16px\"><span style=\"font-family:楷体\">中年女性</span>+间断水肿8年(大于1年) +肌酐升高=慢性肾小球肾炎。患者目前肌酐892μmol/L＞707μmo1/L, 说明患者处于慢性肾衰尿毒症期。对于慢性肾衰竭，肌酐＞442μmo1/L,最有效的治疗是:透析治疗。降压、利尿为一般的对症治疗，对患者不适合。该患者目前无输血的适应症。机体血液中是宁酸勿碱。</span></p>","topic":null,"options":[{"id":5533,"delFlag":false,"createTime":"2019-06-19 17:52:21","updateTime":"2019-06-19 17:52:21","isTrue":false,"questionId":2248,"content":"<p><span style=\";font-family:楷体;font-size:16px\"><span style=\"font-family:楷体\">降压</span></span></p>","selectCnt":0},{"id":5534,"delFlag":false,"createTime":"2019-06-19 17:52:21","updateTime":"2019-06-19 17:52:21","isTrue":true,"questionId":2248,"content":"<p><span style=\";font-family:楷体;font-size:16px\"><span style=\"font-family:楷体\">血液透析</span></span></p>","selectCnt":0},{"id":5535,"delFlag":false,"createTime":"2019-06-19 17:52:21","updateTime":"2019-06-19 17:52:21","isTrue":false,"questionId":2248,"content":"<p><span style=\";font-family:楷体;font-size:16px\"><span style=\"font-family:楷体\">碳酸氢钠</span></span></p>","selectCnt":0},{"id":5536,"delFlag":false,"createTime":"2019-06-19 17:52:21","updateTime":"2019-06-19 17:52:21","isTrue":false,"questionId":2248,"content":"<p><span style=\";font-family:楷体;font-size:16px\"><span style=\"font-family:楷体\">利尿</span></span></p>","selectCnt":0},{"id":5537,"delFlag":false,"createTime":"2019-06-19 17:52:21","updateTime":"2019-06-19 17:52:21","isTrue":false,"questionId":2248,"content":"<p><span style=\";font-family:楷体;font-size:16px\"><span style=\"font-family:楷体\">输血</span></span></p>","selectCnt":0}],"tags":[{"id":927,"delFlag":false,"createTime":"2019-06-09 11:27:22","updateTime":"2019-06-09 11:27:22","name":"181","questionCnt":150,"tagTypeId":46},{"id":946,"delFlag":false,"createTime":"2019-06-09 11:31:57","updateTime":"2019-06-09 11:31:57","name":"泌尿A2","questionCnt":24,"tagTypeId":47}],"hasCollect":false,"userAnswer":null,"questionPath":null},{"id":2202,"createTime":"2019-06-19 17:33:16","topicId":null,"tagId":927,"rule":1,"weight":1,"sort":51,"accuracy":0.0,"content":"<p><span style=\";font-family:楷体;font-size:16px\"><span style=\"font-family:楷体\">，</span>22岁。咽痛、发热伴咳嗽2周，颜面水肿3天。查体: BP150/ 100mmHg，全身皮肤无皮疹。尿常规:蛋白(</span><span style=\";font-family:楷体;font-size:16px\">+</span><span style=\";font-family:楷体;font-size:16px\">+)。尿沉渣镜检: RBC20</span><span style=\";font-family:楷体;font-size:16px\">-</span><span style=\";font-family:楷体;font-size:16px\">30/HP。血肌酐115umol/L,补体C</span><sub><span style=\";font-family:楷体;font-size:16px;vertical-align:sub\">3</span></sub><span style=\";font-family:楷体;font-size:16px\"><span style=\"font-family:楷体\">降低，</span>ASO升高。下列治疗不适宜的是</span></p>","trueCnt":0,"falseCnt":0,"analysis":"<p><span style=\";font-family:楷体;font-size:16px\">①上感史(1-3周) +血尿+补体C</span><sub><span style=\";font-family:楷体;font-size:16px;vertical-align:sub\">3</span></sub><span style=\";font-family:楷体;font-size:16px\"><span style=\"font-family:楷体\">降低</span>=急性肾炎。②急性肾炎是一种自限性疾病，对症支持治疗即可，如抗生素、休息、利尿及控制血压等，但是无需应用激素。③提示:肾病综合征才是首选糖皮质激素，而非急性肾炎的首选药。</span></p>","topic":null,"options":[{"id":5303,"delFlag":false,"createTime":"2019-06-19 17:33:16","updateTime":"2019-06-19 17:33:16","isTrue":false,"questionId":2202,"content":"<p><span style=\";font-family:楷体;font-size:16px\"><span style=\"font-family:楷体\">抗生素</span></span></p>","selectCnt":0},{"id":5304,"delFlag":false,"createTime":"2019-06-19 17:33:16","updateTime":"2019-06-19 17:33:16","isTrue":false,"questionId":2202,"content":"<p><span style=\";font-family:楷体;font-size:16px\"><span style=\"font-family:楷体\">休息</span></span></p>","selectCnt":0},{"id":5305,"delFlag":false,"createTime":"2019-06-19 17:33:16","updateTime":"2019-06-19 17:33:16","isTrue":true,"questionId":2202,"content":"<p><span style=\";font-family:楷体;font-size:16px\"><span style=\"font-family:楷体\">应用激素</span></span></p>","selectCnt":0},{"id":5306,"delFlag":false,"createTime":"2019-06-19 17:33:16","updateTime":"2019-06-19 17:33:16","isTrue":false,"questionId":2202,"content":"<p><span style=\";font-family:楷体;font-size:16px\"><span style=\"font-family:楷体\">利尿</span></span></p>","selectCnt":0},{"id":5307,"delFlag":false,"createTime":"2019-06-19 17:33:16","updateTime":"2019-06-19 17:33:16","isTrue":false,"questionId":2202,"content":"<p><span style=\";font-family:楷体;font-size:16px\"><span style=\"font-family:楷体\">控制血压</span></span></p>","selectCnt":0}],"tags":[{"id":927,"delFlag":false,"createTime":"2019-06-09 11:27:22","updateTime":"2019-06-09 11:27:22","name":"181","questionCnt":150,"tagTypeId":46},{"id":946,"delFlag":false,"createTime":"2019-06-09 11:31:57","updateTime":"2019-06-09 11:31:57","name":"泌尿A2","questionCnt":24,"tagTypeId":47}],"hasCollect":false,"userAnswer":null,"questionPath":null}]}