{"code":200,"msg":"success","data":[{"id":18660,"createTime":"2019-10-31 15:32:52","topicId":null,"tagId":979,"rule":1,"weight":1,"sort":181,"accuracy":0.0,"content":"<p><span style=\";font-family:宋体;font-size:14px\"><span style=\"font-family:宋体\">男性，</span>39岁，商人，有冶游史，1周来发热，头痛，全身不适 ，无食欲，全身淋巴结均肿大，无痛。白细胞3.5×109／L，CD4/CD8 1.0，其他无特殊，此例哪种疾病可能性大</span></p><p><br/></p>","trueCnt":0,"falseCnt":0,"analysis":"<p><span style=\";font-family:宋体;font-size:14px\"><span style=\"font-family:宋体\">患者既往有冶游史，现患者出现发热、头痛、全身淋巴结肿大，白细胞减少，</span>CD4/CD8比例倒置，首先考虑艾滋病。</span></p><p><span style=\";font-family:宋体;font-size:14px\"><span style=\"font-family:宋体\">艾滋病临床表现：</span></span><span style=\";font-family:宋体;font-size:14px\"><span style=\"font-family:宋体\">以发热最常见，可伴有全身不适、头痛、盗汗、恶心、呕吐、腹泻、关节痛、淋巴结肿大及神经系统症状</span></span><span style=\";font-family:宋体;font-size:14px\"><span style=\"font-family:宋体\">。</span></span></p><p><br/></p>","topic":null,"options":[{"id":87446,"delFlag":false,"createTime":"2019-10-31 15:32:52","updateTime":"2019-10-31 15:32:52","isTrue":false,"questionId":18660,"content":"<p><span style=\";font-family:宋体;font-size:14px\"><span style=\"font-family:宋体\">传染性单核细胞增多症</span></span></p>","selectCnt":0},{"id":87447,"delFlag":false,"createTime":"2019-10-31 15:32:52","updateTime":"2019-10-31 15:32:52","isTrue":false,"questionId":18660,"content":"<p><span style=\";font-family:宋体;font-size:14px\"><span style=\"font-family:宋体\">急性淋巴结炎</span></span></p><p></p>","selectCnt":0},{"id":87448,"delFlag":false,"createTime":"2019-10-31 15:32:52","updateTime":"2019-10-31 15:32:52","isTrue":true,"questionId":18660,"content":"<p><span style=\";font-family:宋体;font-size:14px\"><span style=\"font-family:宋体\">艾滋病</span></span></p>","selectCnt":0},{"id":87449,"delFlag":false,"createTime":"2019-10-31 15:32:52","updateTime":"2019-10-31 15:32:52","isTrue":false,"questionId":18660,"content":"<p><span style=\";font-family:宋体;font-size:14px\"><span style=\"font-family:宋体\">霍奇金病</span></span></p>","selectCnt":0},{"id":87450,"delFlag":false,"createTime":"2019-10-31 15:32:52","updateTime":"2019-10-31 15:32:52","isTrue":false,"questionId":18660,"content":"<p><span style=\";font-family:宋体;font-size:14px\"><span style=\"font-family:宋体\">钩体病</span></span></p>","selectCnt":0}],"tags":[{"id":1762,"delFlag":false,"createTime":"2019-10-30 09:54:17","updateTime":"2019-10-30 09:54:17","name":"192","questionCnt":150,"tagTypeId":46},{"id":979,"delFlag":false,"createTime":"2019-06-09 11:36:03","updateTime":"2019-06-09 11:36:03","name":"传染病A2","questionCnt":10,"tagTypeId":47}],"hasCollect":false,"userAnswer":null,"questionPath":null},{"id":11020,"createTime":"2019-06-29 17:05:37","topicId":null,"tagId":929,"rule":1,"weight":1,"sort":180,"accuracy":0.0,"content":"<p><span style=\";font-family:楷体;font-size:16px\"><span style=\"font-family:楷体\">女，</span>30岁。自觉发热，阴道分泌物增多5天，有不洁性接触史。查体：小阴唇皮肤红肿，有圆形小溃疡，分泌物在暗视野显微镜下检查有运动活跃的苍白密螺旋体。应诊断为</span></p><p><br/></p>","trueCnt":0,"falseCnt":0,"analysis":"<p><span style=\";font-family:楷体;font-size:16px\"><span style=\"font-family:楷体\">解析：不洁性接触史</span>+分泌物在暗视野显微镜下检查有运动活跃的苍白密螺旋体=梅毒。</span></p><p><br/></p>","topic":null,"options":[{"id":49289,"delFlag":false,"createTime":"2019-06-29 17:05:37","updateTime":"2019-06-29 17:05:37","isTrue":false,"questionId":11020,"content":"<p><span style=\";font-family:楷体;font-size:16px\"><span style=\"font-family:楷体\">尖锐湿疣</span></span></p>","selectCnt":0},{"id":49290,"delFlag":false,"createTime":"2019-06-29 17:05:37","updateTime":"2019-06-29 17:05:37","isTrue":false,"questionId":11020,"content":"<p><span style=\";font-family:楷体;font-size:16px\"><span style=\"font-family:楷体\">淋病</span></span></p>","selectCnt":0},{"id":49291,"delFlag":false,"createTime":"2019-06-29 17:05:37","updateTime":"2019-06-29 17:05:37","isTrue":true,"questionId":11020,"content":"<p><span style=\";font-family:楷体;font-size:16px\"><span style=\"font-family:楷体\">梅毒</span></span></p>","selectCnt":0},{"id":49292,"delFlag":false,"createTime":"2019-06-29 17:05:37","updateTime":"2019-06-29 17:05:37","isTrue":false,"questionId":11020,"content":"<p><span style=\";font-family:楷体;font-size:16px\"><span style=\"font-family:楷体\">艾滋病</span></span></p>","selectCnt":0},{"id":49293,"delFlag":false,"createTime":"2019-06-29 17:05:37","updateTime":"2019-06-29 17:05:37","isTrue":false,"questionId":11020,"content":"<p><span style=\";font-family:楷体;font-size:16px\"><span style=\"font-family:楷体\">生殖器疱疹</span></span></p>","selectCnt":0}],"tags":[{"id":929,"delFlag":false,"createTime":"2019-06-09 11:27:30","updateTime":"2019-06-09 11:27:30","name":"171","questionCnt":150,"tagTypeId":46},{"id":979,"delFlag":false,"createTime":"2019-06-09 11:36:03","updateTime":"2019-06-09 11:36:03","name":"传染病A2","questionCnt":10,"tagTypeId":47}],"hasCollect":false,"userAnswer":null,"questionPath":null},{"id":10979,"createTime":"2019-06-29 16:45:51","topicId":null,"tagId":929,"rule":1,"weight":1,"sort":165,"accuracy":0.0,"content":"<p><span style=\";font-family:楷体;font-size:16px\"><span style=\"font-family:楷体\">女，</span>40岁。腹痛、腹泻1天。共腹泻10次，为水样便，呕吐1次。查体：T38℃，P112次/分，BP110/70mmhg，轻度脱水貌，腹软，压痛（-）。实验室检查：血WBC9.8×10</span><sup><span style=\";font-family:楷体;font-size:16px;vertical-align:super\">9</span></sup><span style=\";font-family:楷体;font-size:16px\">/L，N0.84，L0.16，粪常规WBC100/H</span><span style=\";font-family:楷体;font-size:16px\">P</span><span style=\";font-family:楷体;font-size:16px\"><span style=\"font-family:楷体\">，</span>RBC6-8/H</span><span style=\";font-family:楷体;font-size:16px\">P</span><span style=\";font-family:楷体;font-size:16px\"><span style=\"font-family:楷体\">。最可能的诊断是</span></span></p><p><br/></p>","trueCnt":0,"falseCnt":0,"analysis":"<p><span style=\";font-family:楷体;font-size:16px\"><span style=\"font-family:楷体\">解析：细菌性痢疾粪便检查：中毒型需及时采便检查。镜检有大量脓</span>(白)细胞(≥15 个/高倍视野) ，少量红细胞可临床诊断，确诊需依靠粪便细菌培养病疾杆菌阳性。懒人</span><span style=\";font-family:楷体;font-size:16px\"><span style=\"font-family:楷体\">出品，必属精品</span></span><span style=\";font-family:楷体;font-size:16px\"><span style=\"font-family:楷体\">。</span></span></p><p><br/></p>","topic":null,"options":[{"id":49084,"delFlag":false,"createTime":"2019-06-29 16:45:51","updateTime":"2019-06-29 16:45:51","isTrue":false,"questionId":10979,"content":"<p><span style=\";font-family:楷体;font-size:16px\"><span style=\"font-family:楷体\">急性肠炎</span></span></p>","selectCnt":0},{"id":49085,"delFlag":false,"createTime":"2019-06-29 16:45:51","updateTime":"2019-06-29 16:45:51","isTrue":true,"questionId":10979,"content":"<p><span style=\";font-family:楷体;font-size:16px\"><span style=\"font-family:楷体\">急性细菌痢疾</span></span></p>","selectCnt":0},{"id":49086,"delFlag":false,"createTime":"2019-06-29 16:45:51","updateTime":"2019-06-29 16:45:51","isTrue":false,"questionId":10979,"content":"<p><span style=\";font-family:楷体;font-size:16px\"><span style=\"font-family:楷体\">溃疡性结肠炎</span></span></p>","selectCnt":0},{"id":49087,"delFlag":false,"createTime":"2019-06-29 16:45:51","updateTime":"2019-06-29 16:45:51","isTrue":false,"questionId":10979,"content":"<p><span style=\";font-family:楷体;font-size:16px\"><span style=\"font-family:楷体\">霍乱</span></span></p>","selectCnt":0},{"id":49088,"delFlag":false,"createTime":"2019-06-29 16:45:51","updateTime":"2019-06-29 16:45:51","isTrue":false,"questionId":10979,"content":"<p><span style=\";font-family:楷体;font-size:16px\"><span style=\"font-family:楷体\">细菌性食物中毒</span></span></p>","selectCnt":0}],"tags":[{"id":929,"delFlag":false,"createTime":"2019-06-09 11:27:30","updateTime":"2019-06-09 11:27:30","name":"171","questionCnt":150,"tagTypeId":46},{"id":979,"delFlag":false,"createTime":"2019-06-09 11:36:03","updateTime":"2019-06-09 11:36:03","name":"传染病A2","questionCnt":10,"tagTypeId":47}],"hasCollect":false,"userAnswer":null,"questionPath":null},{"id":10974,"createTime":"2019-06-29 16:43:47","topicId":null,"tagId":929,"rule":1,"weight":1,"sort":163,"accuracy":0.0,"content":"<p><span style=\";font-family:楷体;font-size:16px\"><span style=\"font-family:楷体\">男，</span>46岁。持续高热5天，伴尿少、腹泻1天。查体：皮肤及巩膜轻度黄染，面部及前胸部轻度充血，双腋下可见细小的出血点。实验室检查：血WBC18.2×10</span><sup><span style=\";font-family:楷体;font-size:16px;vertical-align:super\">9</span></sup><span style=\";font-family:楷体;font-size:16px\">/L,Plt60×10</span><sup><span style=\";font-family:楷体;font-size:16px;vertical-align:super\">9</span></sup><span style=\";font-family:楷体;font-size:16px\">/L，ALT140U/L,TBil45umol/L，尿蛋白（+++）。最可能的诊断是</span></p><p><br/></p>","trueCnt":0,"falseCnt":0,"analysis":"<p><span style=\";font-family:楷体;font-size:16px\"><span style=\"font-family:楷体\">解析：懒人</span></span><span style=\";font-family:楷体;font-size:16px\"><span style=\"font-family:楷体\">出品，必属精品</span></span><span style=\";font-family:楷体;font-size:16px\"><span style=\"font-family:楷体\">。肾综合征出血热又称流行性出血热。是由汉坦病毒引起的一种自然疫源性疾病，典型的临床特征有发热、出血和肾脏损害三大主症，以及发热期、低血压休克期、少尿期、多尿期和恢复期五期经过。</span></span></p><p><br/></p>","topic":null,"options":[{"id":49059,"delFlag":false,"createTime":"2019-06-29 16:43:47","updateTime":"2019-06-29 16:43:47","isTrue":false,"questionId":10974,"content":"<p style=\"margin-left: 24px;\"><span style=\";font-family:楷体;font-size:16px\"><span style=\"font-family:楷体\">流行性脑脊髓膜炎</span></span></p>","selectCnt":0},{"id":49060,"delFlag":false,"createTime":"2019-06-29 16:43:47","updateTime":"2019-06-29 16:43:47","isTrue":false,"questionId":10974,"content":"<p style=\"margin-left: 24px;\"><span style=\";font-family:楷体;font-size:16px\"><span style=\"font-family:楷体\">急性黄疸型肝炎</span></span></p>","selectCnt":0},{"id":49061,"delFlag":false,"createTime":"2019-06-29 16:43:47","updateTime":"2019-06-29 16:43:47","isTrue":false,"questionId":10974,"content":"<p style=\"margin-left: 24px;\"><span style=\";font-family:楷体;font-size:16px\"><span style=\"font-family:楷体\">中毒性细菌性痢疾</span></span></p>","selectCnt":0},{"id":49062,"delFlag":false,"createTime":"2019-06-29 16:43:47","updateTime":"2019-06-29 16:43:47","isTrue":false,"questionId":10974,"content":"<p style=\"margin-left: 24px;\"><span style=\";font-family:楷体;font-size:16px\"><span style=\"font-family:楷体\">钩端螺旋体病</span></span></p>","selectCnt":0},{"id":49063,"delFlag":false,"createTime":"2019-06-29 16:43:47","updateTime":"2019-06-29 16:43:47","isTrue":true,"questionId":10974,"content":"<p><span style=\";font-family:楷体;font-size:16px\"><span style=\"font-family:楷体\">&nbsp; &nbsp;肾综合征出血热</span></span><span style=\";font-family:楷体;font-size:16px\">&nbsp;</span></p>","selectCnt":0}],"tags":[{"id":929,"delFlag":false,"createTime":"2019-06-09 11:27:30","updateTime":"2019-06-09 11:27:30","name":"171","questionCnt":150,"tagTypeId":46},{"id":979,"delFlag":false,"createTime":"2019-06-09 11:36:03","updateTime":"2019-06-09 11:36:03","name":"传染病A2","questionCnt":10,"tagTypeId":47}],"hasCollect":false,"userAnswer":null,"questionPath":null},{"id":10930,"createTime":"2019-06-29 16:25:43","topicId":null,"tagId":929,"rule":1,"weight":1,"sort":149,"accuracy":0.0,"content":"<p><span style=\";font-family:楷体;font-size:16px\"><span style=\"font-family:楷体\">男，</span>15岁。发热3天，嗜睡1天，于2月6日就诊。查体：T39℃，P110次/分，BP100/70mmhg，下至皮肤可见少量瘀点，颈抵抗（+）。实验室检查：脑脊液压力210mmH</span><sub><span style=\";font-family:楷体;font-size:16px;vertical-align:sub\">2</span></sub><span style=\";font-family:楷体;font-size:16px\">O，细胞总数5000×10</span><sup><span style=\";font-family:楷体;font-size:16px;vertical-align:super\">6</span></sup><span style=\";font-family:楷体;font-size:16px\">/L，多核0.90，糖2.2mmol/L,蛋白2g/L。最可能的诊断是</span></p><p><br/></p>","trueCnt":0,"falseCnt":0,"analysis":"<p><span style=\";font-family:楷体;font-size:16px\"><span style=\"font-family:楷体\">解析：流行性脑脊髓膜炎多发生于冬、春季节，有发热、皮肤瘀点、瘀斑，脑脊液外观混浊，白细胞＞</span>1000×10</span><sup><span style=\";font-family:楷体;font-size:16px;vertical-align:super\">6</span></sup><span style=\";font-family:楷体;font-size:16px\">/L，以多核细胞为主，蛋白质明显增高，糖与氯化物明显降低，涂片或培养可查见脑膜炎球菌。懒人</span><span style=\";font-family:楷体;font-size:16px\"><span style=\"font-family:楷体\">出品，必属精品</span></span><span style=\";font-family:楷体;font-size:16px\"><span style=\"font-family:楷体\">。</span></span></p><p><br/></p>","topic":null,"options":[{"id":48839,"delFlag":false,"createTime":"2019-06-29 16:25:43","updateTime":"2019-06-29 16:25:43","isTrue":false,"questionId":10930,"content":"<p><span style=\";font-family:楷体;font-size:16px\"><span style=\"font-family:楷体\">结核性脑膜炎</span></span></p>","selectCnt":0},{"id":48840,"delFlag":false,"createTime":"2019-06-29 16:25:43","updateTime":"2019-06-29 16:25:43","isTrue":true,"questionId":10930,"content":"<p><span style=\";font-family:楷体;font-size:16px\"><span style=\"font-family:楷体\">流行性脑脊髓膜炎</span></span></p>","selectCnt":0},{"id":48841,"delFlag":false,"createTime":"2019-06-29 16:25:43","updateTime":"2019-06-29 16:25:43","isTrue":false,"questionId":10930,"content":"<p><span style=\";font-family:楷体;font-size:16px\"><span style=\"font-family:楷体\">病毒性脑膜炎</span></span></p>","selectCnt":0},{"id":48842,"delFlag":false,"createTime":"2019-06-29 16:25:43","updateTime":"2019-06-29 16:25:43","isTrue":false,"questionId":10930,"content":"<p><span style=\";font-family:楷体;font-size:16px\"><span style=\"font-family:楷体\">流行性乙型脑炎</span></span></p>","selectCnt":0},{"id":48843,"delFlag":false,"createTime":"2019-06-29 16:25:43","updateTime":"2019-06-29 16:25:43","isTrue":false,"questionId":10930,"content":"<p><span style=\";font-family:楷体;font-size:16px\"><span style=\"font-family:楷体\">隐球菌脑膜炎</span></span></p>","selectCnt":0}],"tags":[{"id":929,"delFlag":false,"createTime":"2019-06-09 11:27:30","updateTime":"2019-06-09 11:27:30","name":"171","questionCnt":150,"tagTypeId":46},{"id":979,"delFlag":false,"createTime":"2019-06-09 11:36:03","updateTime":"2019-06-09 11:36:03","name":"传染病A2","questionCnt":10,"tagTypeId":47}],"hasCollect":false,"userAnswer":null,"questionPath":null},{"id":2375,"createTime":"2019-06-20 09:38:12","topicId":null,"tagId":927,"rule":1,"weight":1,"sort":92,"accuracy":0.0,"content":"<p><span style=\";font-family:楷体;font-size:16px\"><span style=\"font-family:楷体\">男，</span>45岁，农民。发热5天，呕吐腹泻伴少尿1天，查体:神志清楚，结膜充血，双腋下可见“搔抓样”出血点。实验室检查:WBC25×10</span><sup><span style=\";font-family:楷体;font-size:16px;vertical-align:super\">9</span></sup><span style=\";font-family:楷体;font-size:16px\">/L，PLt30×10</span><sup><span style=\";font-family:楷体;font-size:16px;vertical-align:super\">9</span></sup><span style=\";font-family:楷体;font-size:16px\">/L,ALT 80U/L,TBil 45umol,尿蛋白(+++)。最可能的诊断是</span></p>","trueCnt":0,"falseCnt":0,"analysis":"<p><span style=\";font-family:楷体;font-size:16px\">1）肾综合征出血热：</span><span style=\";font-family:楷体;letter-spacing:0;font-size:16px\"><span style=\"font-family:楷体\">临床特征包括早期三种主要表现和病程的五期经过。前者为发热中毒症状，充血、出血、外渗征和肾损害。患者热退后症状反而加重。典型病例有发热期、低血压休克期、少尿期、多尿期和恢复期。不典型者可越期或前三期之间重叠。实验室检查包括血液浓缩、血红蛋白和红细胞增高</span>,白细胞计数增高、异型淋巴细胞、血小板减少。尿蛋白大量出现和尿中带膜状物有助于诊断。血清、血细胞和尿中检出肾综合征出血热病毒抗原和血清中检出特异性IgM抗体可以明确诊断。特异性IgG抗体需双份血清效价升高4倍以上者才有诊断意义。反转录-聚合酶链反应( RT-PCR)检测汉坦病毒的RNA有助于早期和非典型患者的诊断。</span></p>","topic":null,"options":[{"id":6162,"delFlag":false,"createTime":"2019-06-20 09:38:12","updateTime":"2019-06-20 09:38:12","isTrue":false,"questionId":2375,"content":"<p><span style=\";font-family:楷体;font-size:16px\"><span style=\"font-family:楷体\">急性细菌性痢疾</span></span></p>","selectCnt":0},{"id":6163,"delFlag":false,"createTime":"2019-06-20 09:38:12","updateTime":"2019-06-20 09:38:12","isTrue":true,"questionId":2375,"content":"<p><span style=\";font-family:楷体;font-size:16px\"><span style=\"font-family:楷体\">肾综合征出血热</span></span></p>","selectCnt":0},{"id":6164,"delFlag":false,"createTime":"2019-06-20 09:38:12","updateTime":"2019-06-20 09:38:12","isTrue":false,"questionId":2375,"content":"<p><span style=\";font-family:楷体;font-size:16px\"><span style=\"font-family:楷体\">钩端螺旋体病</span></span></p>","selectCnt":0},{"id":6165,"delFlag":false,"createTime":"2019-06-20 09:38:12","updateTime":"2019-06-20 09:38:12","isTrue":false,"questionId":2375,"content":"<p><span style=\";font-family:楷体;font-size:16px\"><span style=\"font-family:楷体\">急性黄疸型肝炎</span></span></p>","selectCnt":0},{"id":6166,"delFlag":false,"createTime":"2019-06-20 09:38:12","updateTime":"2019-06-20 09:38:12","isTrue":false,"questionId":2375,"content":"<p><span style=\";font-family:楷体;font-size:16px\"><span style=\"font-family:楷体\">疟疾</span></span></p>","selectCnt":0}],"tags":[{"id":979,"delFlag":false,"createTime":"2019-06-09 11:36:03","updateTime":"2019-06-09 11:36:03","name":"传染病A2","questionCnt":10,"tagTypeId":47},{"id":927,"delFlag":false,"createTime":"2019-06-09 11:27:22","updateTime":"2019-06-09 11:27:22","name":"181","questionCnt":150,"tagTypeId":46}],"hasCollect":false,"userAnswer":null,"questionPath":null},{"id":2320,"createTime":"2019-06-20 09:14:05","topicId":null,"tagId":927,"rule":1,"weight":1,"sort":80,"accuracy":0.0,"content":"<p><span style=\";font-family:楷体;font-size:16px\"><span style=\"font-family:楷体\">男，</span>45岁。发热、腹泻2个月，咳嗽4天。T37.6℃-38.8℃，腹泻4-6次/天,水样便，体重下降5kg。有静脉药史。实验室检查:血CD4</span><sup><span style=\";font-family:楷体;font-size:16px;vertical-align:super\">+</span></sup><span style=\";font-family:楷体;font-size:16px\">T淋巴细胞减少。最可能的诊断是</span></p>","trueCnt":0,"falseCnt":0,"analysis":"<p><span style=\";font-family:楷体;font-size:16px\"><span style=\"font-family:楷体\">艾滋病：艾滋病期为感染</span>HIV后的最终阶段。患者CD4</span><sup><span style=\";font-family:楷体;font-size:16px;vertical-align:super\">+ </span></sup><span style=\";font-family:楷体;font-size:16px\">T淋巴细胞计数明显下降，HIV相关症状:主要表现为持续1个月以上的发热盗汗、腹泻；体重减轻10%以上。部分患者表现为神经精神症状，如记忆力减退、精神淡漠、性格改变头痛、癫痫及痴呆等。</span></p>","topic":null,"options":[{"id":5888,"delFlag":false,"createTime":"2019-06-20 09:14:05","updateTime":"2019-06-20 09:14:05","isTrue":false,"questionId":2320,"content":"<p><span style=\";font-family:楷体;font-size:16px\"><span style=\"font-family:楷体\">慢性细菌性痢疾</span></span></p>","selectCnt":0},{"id":5889,"delFlag":false,"createTime":"2019-06-20 09:14:05","updateTime":"2019-06-20 09:14:05","isTrue":true,"questionId":2320,"content":"<p><span style=\";font-family:楷体;font-size:16px\"><span style=\"font-family:楷体\">艾滋病</span></span></p>","selectCnt":0},{"id":5890,"delFlag":false,"createTime":"2019-06-20 09:14:05","updateTime":"2019-06-20 09:14:05","isTrue":false,"questionId":2320,"content":"<p><span style=\";font-family:楷体;font-size:16px\"><span style=\"font-family:楷体\">肺结核</span></span></p>","selectCnt":0},{"id":5891,"delFlag":false,"createTime":"2019-06-20 09:14:05","updateTime":"2019-06-20 09:14:05","isTrue":false,"questionId":2320,"content":"<p><span style=\";font-family:楷体;font-size:16px\"><span style=\"font-family:楷体\">细菌性肺炎</span></span></p>","selectCnt":0},{"id":5892,"delFlag":false,"createTime":"2019-06-20 09:14:05","updateTime":"2019-06-20 09:14:05","isTrue":false,"questionId":2320,"content":"<p><span style=\";font-family:楷体;font-size:16px\"><span style=\"font-family:楷体\">溃疡性结肠炎</span></span></p>","selectCnt":0}],"tags":[{"id":979,"delFlag":false,"createTime":"2019-06-09 11:36:03","updateTime":"2019-06-09 11:36:03","name":"传染病A2","questionCnt":10,"tagTypeId":47},{"id":927,"delFlag":false,"createTime":"2019-06-09 11:27:22","updateTime":"2019-06-09 11:27:22","name":"181","questionCnt":150,"tagTypeId":46}],"hasCollect":false,"userAnswer":null,"questionPath":null},{"id":2311,"createTime":"2019-06-20 09:09:43","topicId":null,"tagId":927,"rule":1,"weight":1,"sort":77,"accuracy":0.0,"content":"<p><span style=\";font-family:楷体;font-size:16px\"><span style=\"font-family:楷体\">女，</span>45岁。发热、腹痛、腹泻2小时，大便10余次，为脓血便，5小时前曾在小餐馆进食。实验室检查血WBC13.0×10</span><sup><span style=\";font-family:楷体;font-size:16px;vertical-align:super\">9</span></sup><span style=\";font-family:楷体;font-size:16px\">/L, N0.85，L 0.15，镜检: WBC 80/HP, RBC10/HP,最可能的诊断是</span></p>","trueCnt":0,"falseCnt":0,"analysis":"<p><span style=\";font-family:楷体;letter-spacing:0;font-size:16px\"><span style=\"font-family:楷体\">通常根据流行病学史</span>.症状体征及实险室检查进行综合诊断，确诊依赖于病原学的检查。菌痢多发于夏、秋季.有不洁饮食或与菌痢患者接触史。急性期临床表现为发热、腹痛、腹泻、里急后重及黏液脓血便。左下腹有明显压痛。慢性菌痢患者则有急性痢疾史,病程超过2个月而病情未愈。中毒性菌痢以儿童多见,有高热、惊厥意识障碍及呼吸、循环衰竭,起病时胃肠道症状轻微，甚至无腹痛、腹泻。常需盐水灌肠或肛拭子行粪便检查方可诊断。粪便镜检有大量白细胞(≥15个1高倍视野)、脓细胞及红细胞即可诊断。确诊有赖于粪便培养出痢疾杆菌。①急性肠胃炎：</span><span style=\";font-family:楷体;font-size:16px;background:rgb(255,255,255)\"><span style=\"font-family:楷体\">急性</span></span><a href=\"https://baike.baidu.com/item/%E8%83%83%E8%82%A0%E7%82%8E/5803450\"><span style=\";font-family:楷体;font-size:16px;background:rgb(255,255,255)\"><span style=\"font-family:楷体\">胃肠炎</span></span></a><span style=\";font-family:楷体;font-size:16px;background:rgb(255,255,255)\"><span style=\"font-family:楷体\">引起的轻型</span></span><a href=\"https://baike.baidu.com/item/%E8%85%B9%E6%B3%BB/2193261\"><span style=\";font-family:楷体;font-size:16px;background:rgb(255,255,255)\"><span style=\"font-family:楷体\">腹泻</span></span></a><span style=\";font-family:楷体;font-size:16px;background:rgb(255,255,255)\"><span style=\"font-family:楷体\">，一般状况良好，每天大便在</span>10次以下，为黄色或黄绿色，少量黏液或白色皂块，粪质不多，有时大便呈“蛋花汤样”。急性</span><a href=\"https://baike.baidu.com/item/%E8%83%83%E8%82%A0%E7%82%8E/5803450\"><span style=\";font-family:楷体;font-size:16px;background:rgb(255,255,255)\"><span style=\"font-family:楷体\">胃肠炎</span></span></a><span style=\";font-family:楷体;font-size:16px;background:rgb(255,255,255)\"><span style=\"font-family:楷体\">也可以引起较重的</span></span><a href=\"https://baike.baidu.com/item/%E8%85%B9%E6%B3%BB/2193261\"><span style=\";font-family:楷体;font-size:16px;background:rgb(255,255,255)\"><span style=\"font-family:楷体\">腹泻</span></span></a><span style=\";font-family:楷体;font-size:16px;background:rgb(255,255,255)\"><span style=\"font-family:楷体\">，每天大便数次至数十次。大量水样便，少量黏液，恶心呕吐，食欲低下，有时呕吐出咖啡样物。如出现低血钾，可有腹胀，有全身中毒症状；如不规则低热或高热，烦躁不安进而精神不振，意识朦胧，甚至昏迷。</span>②</span><span style=\";font-family:楷体;font-size:16px\"><span style=\"font-family:楷体\">急性阑尾炎：常有转移性右下腹痛</span>,伴恶心、呕吐、发热,及右下腹压痛、反跳痛和腹肌紧张等。③急性病毒性腹泻：腹泻、呕吐与一般症状。轻型病例有食欲减退，大便次数增多，每日数次到10次左右，稀便或带少量水分，淡黄或绿色，稍有酸味，精神尚好，无中毒症状，偶有低热恶心，呕吐，体重不增或略降，有时尿少。严重者水电解质失衡。④食物中毒： 细菌性食物中毒是指由于进食被细菌或细菌毒素所污染的食物而引起的急性感染中毒性疾病 。细菌性食物中毒的特征为:a.在集体用膳单位常呈暴发起病。发病者与食入同一污染食物有明显关系；b.潜伏期短,突然发病。临床表现以急性胃肠炎为主。肉毒杆菌中毒则以眼肌、咽肌瘫痪为主；c.病程较短,多数在2-3天内自愈。d.多发生于夏秋季。</span></p>","topic":null,"options":[{"id":5843,"delFlag":false,"createTime":"2019-06-20 09:09:43","updateTime":"2019-06-20 09:09:43","isTrue":false,"questionId":2311,"content":"<p><span style=\";font-family:楷体;font-size:16px\"><span style=\"font-family:楷体\">急性胃肠炎</span></span></p>","selectCnt":0},{"id":5844,"delFlag":false,"createTime":"2019-06-20 09:09:43","updateTime":"2019-06-20 09:09:43","isTrue":false,"questionId":2311,"content":"<p><span style=\";font-family:楷体;font-size:16px\"><span style=\"font-family:楷体\">急性阑尾炎</span></span></p>","selectCnt":0},{"id":5845,"delFlag":false,"createTime":"2019-06-20 09:09:43","updateTime":"2019-06-20 09:09:43","isTrue":false,"questionId":2311,"content":"<p><span style=\";font-family:楷体;font-size:16px\"><span style=\"font-family:楷体\">急性病毒性腹泻</span></span></p>","selectCnt":0},{"id":5846,"delFlag":false,"createTime":"2019-06-20 09:09:43","updateTime":"2019-06-20 09:09:43","isTrue":true,"questionId":2311,"content":"<p><span style=\";font-family:楷体;font-size:16px\"><span style=\"font-family:楷体\">急性细菌性痢疾</span></span></p>","selectCnt":0},{"id":5847,"delFlag":false,"createTime":"2019-06-20 09:09:43","updateTime":"2019-06-20 09:09:43","isTrue":false,"questionId":2311,"content":"<p><span style=\";font-family:楷体;font-size:16px\"><span style=\"font-family:楷体\">食物中毒</span></span></p>","selectCnt":0}],"tags":[{"id":979,"delFlag":false,"createTime":"2019-06-09 11:36:03","updateTime":"2019-06-09 11:36:03","name":"传染病A2","questionCnt":10,"tagTypeId":47},{"id":927,"delFlag":false,"createTime":"2019-06-09 11:27:22","updateTime":"2019-06-09 11:27:22","name":"181","questionCnt":150,"tagTypeId":46}],"hasCollect":false,"userAnswer":null,"questionPath":null},{"id":2280,"createTime":"2019-06-20 08:48:34","topicId":null,"tagId":927,"rule":1,"weight":1,"sort":64,"accuracy":0.0,"content":"<p><span style=\";font-family:楷体;font-size:16px\"><span style=\"font-family:楷体\">女，</span>31岁，妊娠28周，阴道脓性分泌物增多3天，诊断为淋病。首选的治疗是</span></p>","trueCnt":0,"falseCnt":0,"analysis":"<p><span style=\";font-family:楷体;font-size:16px\"><span style=\"font-family:楷体\">淋病首选头孢曲松钠。对于无并发症淋病，如淋菌性尿道炎、宫颈炎、直肠炎，给予头孢曲松，肌注，单次给药；或大观霉素肌注，单次给药；或头孢噻肟肌注，单次给药。次选方案为其他第三代头孢菌素类，如已证明其疗效较好，亦可选作替代药物。如果沙眼衣原体感染不能排除，加上抗沙眼衣原体感染药物。</span></span><span style=\";font-family:楷体;font-size:16px\">&nbsp;</span></p>","topic":null,"options":[{"id":5688,"delFlag":false,"createTime":"2019-06-20 08:48:34","updateTime":"2019-06-20 08:48:34","isTrue":false,"questionId":2280,"content":"<p><span style=\";font-family:楷体;font-size:16px\"><span style=\"font-family:楷体\">头孢西丁加用红霉素</span></span></p>","selectCnt":0},{"id":5689,"delFlag":false,"createTime":"2019-06-20 08:48:34","updateTime":"2019-06-20 08:48:34","isTrue":true,"questionId":2280,"content":"<p><span style=\";font-family:楷体;font-size:16px\"><span style=\"font-family:楷体\">头孢曲松钠单次肌肉注射</span></span></p>","selectCnt":0},{"id":5690,"delFlag":false,"createTime":"2019-06-20 08:48:34","updateTime":"2019-06-20 08:48:34","isTrue":false,"questionId":2280,"content":"<p><span style=\";font-family:楷体;font-size:16px\"><span style=\"font-family:楷体\">头孢曲松钠加用四环素</span></span></p>","selectCnt":0},{"id":5691,"delFlag":false,"createTime":"2019-06-20 08:48:34","updateTime":"2019-06-20 08:48:34","isTrue":false,"questionId":2280,"content":"<p><span style=\";font-family:楷体;font-size:16px\"><span style=\"font-family:楷体\">头孢西丁单次给药</span></span></p>","selectCnt":0},{"id":5692,"delFlag":false,"createTime":"2019-06-20 08:48:34","updateTime":"2019-06-20 08:48:34","isTrue":false,"questionId":2280,"content":"<p><span style=\";font-family:楷体;font-size:16px\"><span style=\"font-family:楷体\">头孢曲松钠加用喹诺酮类药物</span></span></p>","selectCnt":0}],"tags":[{"id":979,"delFlag":false,"createTime":"2019-06-09 11:36:03","updateTime":"2019-06-09 11:36:03","name":"传染病A2","questionCnt":10,"tagTypeId":47},{"id":927,"delFlag":false,"createTime":"2019-06-09 11:27:22","updateTime":"2019-06-09 11:27:22","name":"181","questionCnt":150,"tagTypeId":46}],"hasCollect":false,"userAnswer":null,"questionPath":null},{"id":1895,"createTime":"2019-06-19 14:53:25","topicId":null,"tagId":931,"rule":1,"weight":1,"sort":92,"accuracy":0.0,"content":"<p><span style=\";font-family:楷体;font-size:12px\"><span style=\"font-family:楷体\">男，</span>35岁，农民。持续高热、头痛、腰痛、尿少3天入院。查体：神志清楚，皮肤及巩膜轻度黄染，面部及前胸明显充血，双腋下可见“鞭击样”出血点。实验室检查：WBC14.2</span><span style=\";font-family:楷体;font-size:12px\">×</span><span style=\";font-family:楷体;font-size:12px\">10</span><sup><span style=\";font-family:楷体;font-size:12px;vertical-align:super\">9</span></sup><span style=\";font-family:楷体;font-size:12px\">/L，Plt50</span><span style=\";font-family:楷体;font-size:12px\">×</span><span style=\";font-family:楷体;font-size:12px\">10</span><sup><span style=\";font-family:楷体;font-size:12px;vertical-align:super\">9</span></sup><span style=\";font-family:楷体;font-size:12px\">/L，Alt240U/L，TBil145μmol/L，尿蛋白（++）。最可能的诊断是</span></p><p><br/></p>","trueCnt":0,"falseCnt":0,"analysis":"<p><span style=\";font-family:楷体;font-size:12px\"><span style=\"font-family:楷体\">解析：肾综合征出血热：起病急，有</span>&quot;三大主症&quot;（发热、出血、肾脏损害）和五期经过者可临床诊断。病初的发热、中毒症状、&quot;三痛症&quot;、&quot;三红症&quot;、酒醉貌、皮肤黏膜出血及热退后症状加重和肾脏损害等表现，均有助于本病的早期诊断。</span></p>","topic":null,"options":[{"id":3770,"delFlag":false,"createTime":"2019-06-19 14:53:25","updateTime":"2019-06-19 14:53:25","isTrue":false,"questionId":1895,"content":"<p><span style=\";font-family:楷体;font-size:12px\"><span style=\"font-family:楷体\">急性黄疸型肝炎</span></span></p>","selectCnt":0},{"id":3771,"delFlag":false,"createTime":"2019-06-19 14:53:25","updateTime":"2019-06-19 14:53:25","isTrue":true,"questionId":1895,"content":"<p><span style=\";font-family:楷体;font-size:12px\"><span style=\"font-family:楷体\">肾综合征出血热</span></span></p>","selectCnt":0},{"id":3772,"delFlag":false,"createTime":"2019-06-19 14:53:25","updateTime":"2019-06-19 14:53:25","isTrue":false,"questionId":1895,"content":"<p><span style=\";font-family:楷体;font-size:12px\"><span style=\"font-family:楷体\">钩端螺旋体病</span></span></p>","selectCnt":0},{"id":3773,"delFlag":false,"createTime":"2019-06-19 14:53:25","updateTime":"2019-06-19 14:53:25","isTrue":false,"questionId":1895,"content":"<p><span style=\";font-family:楷体;font-size:12px\"><span style=\"font-family:楷体\">流行乙型脑炎</span></span></p>","selectCnt":0},{"id":3774,"delFlag":false,"createTime":"2019-06-19 14:53:25","updateTime":"2019-06-19 14:53:25","isTrue":false,"questionId":1895,"content":"<p><span style=\";font-family:楷体;font-size:12px\"><span style=\"font-family:楷体\">疟疾</span></span></p>","selectCnt":0}],"tags":[{"id":979,"delFlag":false,"createTime":"2019-06-09 11:36:03","updateTime":"2019-06-09 11:36:03","name":"传染病A2","questionCnt":10,"tagTypeId":47},{"id":931,"delFlag":false,"createTime":"2019-06-09 11:27:38","updateTime":"2019-06-09 11:27:38","name":"161","questionCnt":150,"tagTypeId":46}],"hasCollect":false,"userAnswer":null,"questionPath":null}]}